[
    {
        "DiaChi": "Đường Huỳnh Tấn Phát, Thị trấn Nhà Bè, Huyện Nhà Bè, Tp Hồ Chí Minh",
        "LoaiHinhDat": "Đất thổ cư",
        "DienTichDat": "86 m²",
        "Gia/M2": "55 triệu/m²",
        "GiayToPhapLy": "Đã có sổ",
        "DacDiemNha/Dat": "Thổ cư toàn bộ\nNở hậu",
        "ChieuNgang": "8.3 m",
        "ChieuDai": "11 m",
        "DonVi(M2/Hecta)": "m²"
    },
    {
        "DiaChi": "Đường Quốc lộ 51, Phường Phước Tân, Thành phố Biên Hòa, Đồng Nai",
        "LoaiHinhDat": "Đất thổ cư",
        "DienTichDat": "100 m²",
        "Gia/M2": "8 triệu/m²",
        "GiayToPhapLy": "Giấy tờ viết tay",
        "ChieuNgang": "5 m",
        "ChieuDai": "20 m"
    },
    {
        "DiaChi": "Đường Long Thuận, Phường Trường Thạnh (Quận 9 cũ), Thành phố Thủ Đức, Tp Hồ Chí Minh",
        "LoaiHinhDat": "Đất thổ cư",
        "DienTichDat": "64 m²",
        "Gia/M2": "50,78 triệu/m²",
        "GiayToPhapLy": "Đã có sổ",
        "DacDiemNha/Dat": "Hẻm xe hơi"
    },
    {
        "DiaChi": "Mương khai, Phường Long Tuyền, Quận Bình Thuỷ, Cần Thơ",
        "LoaiHinhDat": "Đất thổ cư",
        "DienTichDat": "88 m²",
        "Gia/M2": "30,11 triệu/m²",
        "GiayToPhapLy": "Đã có sổ",
        "HuongDat": "Tây Nam",
        "DacDiemNha/Dat": "Mặt tiền",
        "ChieuNgang": "4 m",
        "ChieuDai": "22 m"
    },
    {
        "DiaChi": "Đường Quốc lộ 1, Thị trấn Trảng Bom, Huyện Trảng Bom, Đồng Nai",
        "LoaiHinhDat": "Đất nền dự án",
        "DienTichDat": "95 m²",
        "Gia/M2": "15,26 triệu/m²",
        "GiayToPhapLy": "Đã có sổ",
        "DacDiemNha/Dat": "Mặt tiền",
        "ChieuNgang": "5 m",
        "ChieuDai": "19 m",
        "DonVi(M2/Hecta)": "m²"
    },
    {
        "DiaChi": "Tây Hòa 4, Xã Tây Hoà, Huyện Trảng Bom, Đồng Nai",
        "LoaiHinhDat": "Đất thổ cư",
        "DienTichDat": "221 m²",
        "Gia/M2": "9,28 triệu/m²",
        "GiayToPhapLy": "Đã có sổ",
        "DacDiemNha/Dat": "Mặt tiền",
        "ChieuNgang": "8 m",
        "DonVi(M2/Hecta)": "m²"
    },
    {
        "DiaChi": "Tây Hòa 7, Xã Tây Hoà, Huyện Trảng Bom, Đồng Nai",
        "LoaiHinhDat": "Đất thổ cư",
        "DienTichDat": "112 m²",
        "Gia/M2": "8,75 triệu/m²",
        "GiayToPhapLy": "Đã có sổ",
        "ChieuNgang": "5 m",
        "ChieuDai": "23 m",
        "DonVi(M2/Hecta)": "m²"
    },
    {
        "DiaChi": "Đường Trảng Bom - Đồi 61, Xã Đồi 61, Huyện Trảng Bom, Đồng Nai",
        "LoaiHinhDat": "Đất thổ cư",
        "DienTichDat": "100 m²",
        "Gia/M2": "8,35 triệu/m²",
        "GiayToPhapLy": "Đã có sổ",
        "ChieuNgang": "5 m",
        "ChieuDai": "20 m",
        "DonVi(M2/Hecta)": "m²"
    },
    {
        "DiaChi": "Đường Trảng Bom - Đồi 61, Xã Đồi 61, Huyện Trảng Bom, Đồng Nai",
        "LoaiHinhDat": "Đất thổ cư",
        "DienTichDat": "600 m²",
        "Gia/M2": "4,50 triệu/m²",
        "GiayToPhapLy": "Đã có sổ",
        "ChieuNgang": "11 m"
    },
    {
        "DiaChi": "Đường Võ Nguyên Giáp, Phường Phước Tân, Thành phố Biên Hòa, Đồng Nai",
        "LoaiHinhDat": "Đất thổ cư",
        "DienTichDat": "528 m²",
        "Gia/M2": "10,23 triệu/m²",
        "GiayToPhapLy": "Đã có sổ",
        "DacDiemNha/Dat": "Mặt tiền",
        "DonVi(M2/Hecta)": "m²"
    },
    {
        "DiaChi": "Đường Lê Văn Lương, Xã Phước Kiển, Huyện Nhà Bè, Tp Hồ Chí Minh",
        "LoaiHinhDat": "Đất thổ cư",
        "DienTichDat": "93 m²",
        "Gia/M2": "82,26 triệu/m²",
        "GiayToPhapLy": "Đã có sổ",
        "ChieuNgang": "5 m",
        "ChieuDai": "18.6 m",
        "DonVi(M2/Hecta)": "m²"
    },
    {
        "DiaChi": "Đường Lê Văn Lương, Xã Phước Kiển, Huyện Nhà Bè, Tp Hồ Chí Minh",
        "LoaiHinhDat": "Đất thổ cư",
        "DienTichDat": "80 m²",
        "Gia/M2": "43,75 triệu/m²",
        "GiayToPhapLy": "Đã có sổ",
        "ChieuNgang": "7.8 m",
        "ChieuDai": "10.5 m",
        "DonVi(M2/Hecta)": "m²"
    },
    {
        "DiaChi": "Tân Lập, Xã Đông La, Huyện Hoài Đức, Hà Nội",
        "LoaiHinhDat": "Đất thổ cư",
        "DienTichDat": "75 m²",
        "Gia/M2": "126,67 triệu/m²",
        "GiayToPhapLy": "Đã có sổ",
        "ChieuNgang": "6.2 m",
        "ChieuDai": "12.2 m"
    },
    {
        "DiaChi": "Hố Truông 1, Phường Hòa Minh, Quận Liên Chiểu, Đà Nẵng",
        "LoaiHinhDat": "Đất thổ cư",
        "DienTichDat": "88 m²",
        "Gia/M2": "43,75 triệu/m²",
        "GiayToPhapLy": "Đã có sổ",
        "ChieuNgang": "5 m",
        "ChieuDai": "17.6 m",
        "DonVi(M2/Hecta)": "m²"
    },
    {
        "DiaChi": "Đường Phan Bá Phiến, Phường Thọ Quang, Quận Sơn Trà, Đà Nẵng",
        "LoaiHinhDat": "Đất thổ cư",
        "DienTichDat": "125 m²",
        "Gia/M2": "54,40 triệu/m²",
        "GiayToPhapLy": "Đã có sổ",
        "DacDiemNha/Dat": "Mặt tiền",
        "ChieuNgang": "5 m",
        "ChieuDai": "25 m"
    },
    {
        "DiaChi": "Đường Phan Khoang, Phường Hòa An, Quận Cẩm Lệ, Đà Nẵng",
        "LoaiHinhDat": "Đất thổ cư",
        "DienTichDat": "75 m²",
        "Gia/M2": "35,60 triệu/m²",
        "GiayToPhapLy": "Đã có sổ",
        "ChieuNgang": "5 m",
        "DonVi(M2/Hecta)": "m²"
    },
    {
        "DiaChi": "Đường Số 2, Xã Lợi Bình Nhơn, Thành phố Tân An, Long An",
        "LoaiHinhDat": "Đất thổ cư",
        "DienTichDat": "90 m²",
        "Gia/M2": "15,56 triệu/m²",
        "GiayToPhapLy": "Đã có sổ",
        "DacDiemNha/Dat": "Mặt tiền",
        "ChieuNgang": "4.5 m",
        "ChieuDai": "20 m"
    },
    {
        "DiaChi": "Đường số 13, Phường 6, Thành phố Tân An, Long An",
        "LoaiHinhDat": "Đất thổ cư",
        "DienTichDat": "100 m²",
        "Gia/M2": "18,60 triệu/m²",
        "GiayToPhapLy": "Đã có sổ",
        "DacDiemNha/Dat": "Mặt tiền",
        "ChieuNgang": "5 m",
        "ChieuDai": "20 m"
    },
    {
        "DiaChi": "Đường Lương Trúc Đàm, Phường Hòa Minh, Quận Liên Chiểu, Đà Nẵng",
        "LoaiHinhDat": "Đất thổ cư",
        "DienTichDat": "110 m²",
        "Gia/M2": "50 triệu/m²",
        "GiayToPhapLy": "Đã có sổ",
        "DacDiemNha/Dat": "Mặt tiền",
        "ChieuNgang": "5 m",
        "ChieuDai": "22 m",
        "DonVi(M2/Hecta)": "m²"
    },
    {
        "DiaChi": "Đường tỉnh 824, Xã Mỹ Hạnh Nam, Huyện Đức Hòa, Long An",
        "LoaiHinhDat": "Đất thổ cư",
        "DienTichDat": "100 m²",
        "Gia/M2": "16 triệu/m²",
        "GiayToPhapLy": "Đã có sổ",
        "DacDiemNha/Dat": "Mặt tiền\nThổ cư toàn bộ",
        "ChieuNgang": "5 m",
        "ChieuDai": "20 m",
        "DonVi(M2/Hecta)": "m²"
    },
    {
        "DiaChi": "Đường Huỳnh Văn Lũy, Phường Phú Lợi, Thành phố Thủ Dầu Một, Bình Dương",
        "LoaiHinhDat": "Đất thổ cư",
        "DienTichDat": "106 m²",
        "Gia/M2": "25,94 triệu/m²",
        "GiayToPhapLy": "Đã có sổ"
    },
    {
        "DiaChi": "Đường Hai Bà Trưng, Phường Đông Hòa, Thành phố Dĩ An, Bình Dương",
        "LoaiHinhDat": "Đất thổ cư",
        "DienTichDat": "96 m²",
        "Gia/M2": "80,21 triệu/m²",
        "GiayToPhapLy": "Đã có sổ",
        "DacDiemNha/Dat": "Mặt tiền\nHẻm xe hơi\nNở hậu",
        "ChieuNgang": "5 m",
        "ChieuDai": "19 m",
        "DonVi(M2/Hecta)": "m²"
    },
    {
        "DiaChi": "Đường Số 8, Phường 17, Quận Gò Vấp, Tp Hồ Chí Minh",
        "LoaiHinhDat": "Đất thổ cư",
        "DienTichDat": "92.4 m²",
        "Gia/M2": "72,51 triệu/m²",
        "GiayToPhapLy": "Đã có sổ",
        "DacDiemNha/Dat": "Hẻm xe hơi\nThổ cư toàn bộ",
        "ChieuNgang": "4 m",
        "ChieuDai": "23 m",
        "DonVi(M2/Hecta)": "m²"
    },
    {
        "DiaChi": "Đường Nguyễn Văn Tỏ, Phường Long Bình Tân, Thành phố Biên Hòa, Đồng Nai",
        "LoaiHinhDat": "Đất thổ cư",
        "DienTichDat": "101 m²",
        "Gia/M2": "29,70 triệu/m²",
        "GiayToPhapLy": "Đã có sổ",
        "DacDiemNha/Dat": "Hẻm xe hơi\nThổ cư toàn bộ",
        "DonVi(M2/Hecta)": "m²"
    },
    {
        "DiaChi": "Đường Quốc lộ 14B mở rộng, Xã Hòa Khương, Huyện Hòa Vang, Đà Nẵng",
        "LoaiHinhDat": "Đất thổ cư",
        "DienTichDat": "150 m²",
        "Gia/M2": "5,80 triệu/m²",
        "GiayToPhapLy": "Đã có sổ",
        "DacDiemNha/Dat": "Mặt tiền\nHẻm xe hơi\nNở hậu",
        "ChieuNgang": "6 m",
        "ChieuDai": "25 m",
        "DonVi(M2/Hecta)": "m²"
    },
    {
        "DiaChi": "Đường Trần Văn Sắc, Phường Phú Thứ, Quận Cái Răng, Cần Thơ",
        "LoaiHinhDat": "Đất thổ cư",
        "DienTichDat": "103 m²",
        "Gia/M2": "27,48 triệu/m²",
        "GiayToPhapLy": "Đã có sổ",
        "HuongDat": "Đông Nam",
        "ChieuNgang": "4.5 m",
        "ChieuDai": "23 m",
        "DonVi(M2/Hecta)": "m²"
    },
    {
        "DiaChi": "Đường Mỹ Đình, Phường Mỹ Đình 2, Quận Nam Từ Liêm, Hà Nội",
        "LoaiHinhDat": "Đất thổ cư",
        "DienTichDat": "86 m²",
        "Gia/M2": "272,09 triệu/m²",
        "GiayToPhapLy": "Đã có sổ",
        "DacDiemNha/Dat": "Hẻm xe hơi\nMặt tiền"
    },
    {
        "DiaChi": "Đường Huỳnh Thị Lung, Xã Nhơn Thạnh Trung, Thành phố Tân An, Long An",
        "LoaiHinhDat": "Đất thổ cư",
        "DienTichDat": "187 m²",
        "Gia/M2": "4,65 triệu/m²",
        "GiayToPhapLy": "Đã có sổ",
        "HuongDat": "Tây Bắc",
        "DacDiemNha/Dat": "Mặt tiền",
        "ChieuNgang": "6.5 m",
        "ChieuDai": "39 m"
    },
    {
        "DiaChi": "Đường Bùi Hữu Nghĩa, Phường Tân Hạnh, Thành phố Biên Hòa, Đồng Nai",
        "LoaiHinhDat": "Đất thổ cư",
        "DienTichDat": "127 m²",
        "Gia/M2": "20,08 triệu/m²",
        "GiayToPhapLy": "Đã có sổ",
        "HuongDat": "Tây",
        "DacDiemNha/Dat": "Hẻm xe hơi\nThổ cư toàn bộ",
        "ChieuNgang": "7.2 m",
        "ChieuDai": "76 m",
        "TenPhanKhu": "Phân Khu 3"
    },
    {
        "DiaChi": "Đường Vành Đai, Xã Lợi Bình Nhơn, Thành phố Tân An, Long An",
        "LoaiHinhDat": "Đất thổ cư",
        "DienTichDat": "119 m²",
        "Gia/M2": "5,80 triệu/m²",
        "GiayToPhapLy": "Đã có sổ",
        "HuongDat": "Nam",
        "DacDiemNha/Dat": "Mặt tiền",
        "ChieuNgang": "5 m",
        "ChieuDai": "24 m"
    },
    {
        "DiaChi": "B4, Phường Phú Thứ, Quận Cái Răng, Cần Thơ",
        "LoaiHinhDat": "Đất thổ cư",
        "DienTichDat": "118 m²",
        "Gia/M2": "19,07 triệu/m²",
        "GiayToPhapLy": "Đã có sổ",
        "HuongDat": "Đông Nam",
        "ChieuNgang": "6 m",
        "ChieuDai": "20 m",
        "DonVi(M2/Hecta)": "m²"
    },
    {
        "DiaChi": "Độ Tràng, Xã Đại Thành, Huyện Quốc Oai, Hà Nội",
        "LoaiHinhDat": "Đất thổ cư",
        "DienTichDat": "80 m²",
        "Gia/M2": "43,75 triệu/m²",
        "GiayToPhapLy": "Đã có sổ",
        "ChieuNgang": "6.2 m",
        "ChieuDai": "13 m"
    },
    {
        "DiaChi": "Đường Thuận Giao 15, Phường Thuận Giao, Thành phố Thuận An, Bình Dương",
        "LoaiHinhDat": "Đất thổ cư",
        "DienTichDat": "826 m²",
        "Gia/M2": "9,20 triệu/m²",
        "GiayToPhapLy": "Đã có sổ",
        "HuongDat": "Tây Bắc",
        "DacDiemNha/Dat": "Hẻm xe hơi\nThổ cư 1 phần",
        "ChieuNgang": "15 m",
        "ChieuDai": "55 m",
        "DonVi(M2/Hecta)": "m²"
    },
    {
        "DiaChi": "Anh Thơ Và Lê Hy Cát, Phường Khuê Mỹ, Quận Ngũ Hành Sơn, Đà Nẵng",
        "LoaiHinhDat": "Đất thổ cư",
        "DienTichDat": "359.5 m²",
        "Gia/M2": "72,32 triệu/m²",
        "GiayToPhapLy": "Đã có sổ",
        "HuongDat": "Đông Bắc",
        "DacDiemNha/Dat": "Mặt tiền",
        "ChieuNgang": "18.3 m",
        "ChieuDai": "20 m"
    },
    {
        "DiaChi": "B14, Phường Phú Thứ, Quận Cái Răng, Cần Thơ",
        "LoaiHinhDat": "Đất thổ cư",
        "DienTichDat": "80 m²",
        "Gia/M2": "26,88 triệu/m²",
        "GiayToPhapLy": "Đã có sổ",
        "HuongDat": "Tây Nam",
        "ChieuNgang": "4 m",
        "ChieuDai": "20 m",
        "DonVi(M2/Hecta)": "m²"
    },
    {
        "DiaChi": "Đường Quốc lộ 27C, Xã Đạ Chais, Huyện Lạc Dương, Lâm Đồng",
        "LoaiHinhDat": "Đất nông nghiệp",
        "DienTichDat": "3000 m²",
        "Gia/M2": "133.000 đ/m²",
        "GiayToPhapLy": "Đã có sổ",
        "ChieuNgang": "50 m",
        "ChieuDai": "60 m"
    },
    {
        "DiaChi": "d1, Phường Hưng Thạnh, Quận Cái Răng, Cần Thơ",
        "LoaiHinhDat": "Đất thổ cư",
        "DienTichDat": "85 m²",
        "Gia/M2": "45,88 triệu/m²",
        "GiayToPhapLy": "Đã có sổ",
        "HuongDat": "Tây Nam",
        "ChieuNgang": "5 m",
        "ChieuDai": "17 m",
        "DonVi(M2/Hecta)": "m²"
    },
    {
        "DiaChi": "Đường Láng Cẫm, ấp Đức Hạnh 1, Xã Đức Lập Hạ, Huyện Đức Hòa, Long An",
        "LoaiHinhDat": "Đất nông nghiệp",
        "DienTichDat": "1000 m²",
        "Gia/M2": "4,20 triệu/m²",
        "GiayToPhapLy": "Đã có sổ",
        "HuongDat": "Bắc",
        "DacDiemNha/Dat": "Chưa có thổ cư\nHẻm xe hơi",
        "ChieuNgang": "20 m",
        "ChieuDai": "50 m",
        "TenPhanKhu": "1/50 mét Đường Láng Cẫm\n ấp Đức Hạnh 1\n xã Đức Lập Hạ\n huyện Đức Hòa\n Long An",
        "DonVi(M2/Hecta)": "m²"
    },
    {
        "DiaChi": "Lê Đình Kỵ, Phường Hòa An, Quận Cẩm Lệ, Đà Nẵng",
        "LoaiHinhDat": "Đất thổ cư",
        "DienTichDat": "100 m²",
        "Gia/M2": "35 triệu/m²",
        "GiayToPhapLy": "Đã có sổ",
        "ChieuNgang": "5 m",
        "ChieuDai": "20 m",
        "DonVi(M2/Hecta)": "m²"
    },
    {
        "DiaChi": "A1, Xã Tân Phước Hưng, Huyện Phụng Hiệp, Hậu Giang",
        "LoaiHinhDat": "Đất nông nghiệp",
        "DienTichDat": "1700 m²",
        "Gia/M2": "129.411 đ/m²",
        "GiayToPhapLy": "Đã có sổ",
        "HuongDat": "Đông",
        "ChieuNgang": "12 m",
        "ChieuDai": "115 m",
        "DonVi(M2/Hecta)": "m²"
    },
    {
        "DiaChi": "8, Dt741, Xã An Bình, Huyện Phú Giáo, Bình Dương",
        "LoaiHinhDat": "Đất thổ cư",
        "DienTichDat": "270 m²",
        "Gia/M2": "1,03 triệu/m²",
        "GiayToPhapLy": "Đã có sổ",
        "HuongDat": "Đông Bắc",
        "DacDiemNha/Dat": "Mặt tiền\nNở hậu\nThổ cư toàn bộ",
        "ChieuNgang": "5 m",
        "ChieuDai": "54 m",
        "TenPhanKhu": "Bd",
        "DonVi(M2/Hecta)": "m²"
    },
    {
        "DiaChi": "Tân Hạnh, Xã Hòa Phước, Huyện Hòa Vang, Đà Nẵng",
        "LoaiHinhDat": "Đất thổ cư",
        "DienTichDat": "135 m²",
        "Gia/M2": "8,52 triệu/m²",
        "GiayToPhapLy": "Đã có sổ",
        "HuongDat": "Tây Bắc",
        "DacDiemNha/Dat": "Mặt tiền",
        "ChieuNgang": "5 m",
        "ChieuDai": "26 m"
    },
    {
        "DiaChi": "Đường Hương Lộ 2, Phường Bình Trị Đông A, Quận Bình Tân, Tp Hồ Chí Minh",
        "LoaiHinhDat": "Đất thổ cư",
        "DienTichDat": "72 m²",
        "Gia/M2": "65 triệu/m²",
        "GiayToPhapLy": "Đã có sổ",
        "DacDiemNha/Dat": "Hẻm xe hơi",
        "ChieuNgang": "4 m",
        "ChieuDai": "18 m"
    },
    {
        "DiaChi": "Đường Y Wang, Xã Ea Kao, Thành phố Buôn Ma Thuột, Đắk Lắk",
        "LoaiHinhDat": "Đất thổ cư",
        "DienTichDat": "277 m²",
        "Gia/M2": "2,02 triệu/m²",
        "GiayToPhapLy": "Đã có sổ",
        "DacDiemNha/Dat": "Hẻm xe hơi\nThổ cư 1 phần",
        "ChieuNgang": "5 m",
        "ChieuDai": "58 m",
        "DonVi(M2/Hecta)": "m²"
    },
    {
        "DiaChi": "668, Đường Nguyễn Thị Hẹ, Xã Trung Lập Thượng, Huyện Củ Chi, Tp Hồ Chí Minh",
        "LoaiHinhDat": "Đất thổ cư",
        "DienTichDat": "1000 m²",
        "Gia/M2": "3,95 triệu/m²",
        "GiayToPhapLy": "Đã có sổ",
        "HuongDat": "Nam",
        "DacDiemNha/Dat": "Mặt tiền",
        "ChieuNgang": "18 m",
        "ChieuDai": "60 m",
        "DonVi(M2/Hecta)": "m²"
    },
    {
        "DiaChi": "13, quốc lộ, Xã An Lập, Huyện Dầu Tiếng, Bình Dương",
        "LoaiHinhDat": "Đất nông nghiệp",
        "DienTichDat": "3658 m²",
        "Gia/M2": "259.704 đ/m²",
        "GiayToPhapLy": "Đã có sổ",
        "DacDiemNha/Dat": "Mặt tiền\nNở hậu\nChưa có thổ cư",
        "ChieuNgang": "52 m",
        "ChieuDai": "75 m",
        "DonVi(M2/Hecta)": "m²"
    },
    {
        "DiaChi": "Nguyễn Huy Tưởng, Phường Hòa Minh, Quận Liên Chiểu, Đà Nẵng",
        "LoaiHinhDat": "Đất thổ cư",
        "DienTichDat": "88 m²",
        "Gia/M2": "31,25 triệu/m²",
        "GiayToPhapLy": "Đã có sổ",
        "ChieuNgang": "4.5 m",
        "ChieuDai": "19.5 m",
        "DonVi(M2/Hecta)": "m²"
    },
    {
        "DiaChi": "Thạnh Xuân 22, Phường Thạnh Xuân, Quận 12, Tp Hồ Chí Minh",
        "LoaiHinhDat": "Đất thổ cư",
        "DienTichDat": "117 m²",
        "Gia/M2": "42,65 triệu/m²",
        "GiayToPhapLy": "Đã có sổ",
        "DacDiemNha/Dat": "Hẻm xe hơi",
        "ChieuNgang": "5.8 m",
        "ChieuDai": "19 m",
        "DonVi(M2/Hecta)": "m²"
    },
    {
        "DiaChi": "Đường Tô Ngọc Vân, Phường Thạnh Xuân, Quận 12, Tp Hồ Chí Minh",
        "LoaiHinhDat": "Đất thổ cư",
        "DienTichDat": "62 m²",
        "Gia/M2": "56,45 triệu/m²",
        "GiayToPhapLy": "Đã có sổ",
        "DacDiemNha/Dat": "Hẻm xe hơi",
        "ChieuNgang": "4 m",
        "ChieuDai": "15.5 m",
        "DonVi(M2/Hecta)": "m²"
    },
    {
        "DiaChi": "Thạnh Xuân 52, Phường Thạnh Xuân, Quận 12, Tp Hồ Chí Minh",
        "LoaiHinhDat": "Đất thổ cư",
        "DienTichDat": "52 m²",
        "Gia/M2": "55,19 triệu/m²",
        "GiayToPhapLy": "Đã có sổ",
        "DacDiemNha/Dat": "Hẻm xe hơi",
        "ChieuNgang": "4 m",
        "ChieuDai": "13 m",
        "DonVi(M2/Hecta)": "m²"
    },
    {
        "DiaChi": "Thạnh Xuân 52, Phường Thạnh Xuân, Quận 12, Tp Hồ Chí Minh",
        "LoaiHinhDat": "Đất thổ cư",
        "DienTichDat": "88 m²",
        "Gia/M2": "40,91 triệu/m²",
        "GiayToPhapLy": "Đã có sổ",
        "DacDiemNha/Dat": "Hẻm xe hơi",
        "ChieuNgang": "5.6 m",
        "ChieuDai": "13.5 m",
        "DonVi(M2/Hecta)": "m²"
    },
    {
        "DiaChi": "Đường Thạnh Lộc 37, Phường Thạnh Lộc, Quận 12, Tp Hồ Chí Minh",
        "LoaiHinhDat": "Đất thổ cư",
        "DienTichDat": "76 m²",
        "Gia/M2": "42,11 triệu/m²",
        "GiayToPhapLy": "Đã có sổ",
        "DacDiemNha/Dat": "Hẻm xe hơi",
        "ChieuNgang": "4 m",
        "ChieuDai": "19 m",
        "DonVi(M2/Hecta)": "m²"
    },
    {
        "DiaChi": "Thạnh Xuân 25, Phường Thạnh Xuân, Quận 12, Tp Hồ Chí Minh",
        "LoaiHinhDat": "Đất thổ cư",
        "DienTichDat": "100 m²",
        "Gia/M2": "43 triệu/m²",
        "GiayToPhapLy": "Đã có sổ",
        "DacDiemNha/Dat": "Hẻm xe hơi",
        "ChieuNgang": "4 m",
        "ChieuDai": "25 m",
        "DonVi(M2/Hecta)": "m²"
    },
    {
        "DiaChi": "đường bê tông suối nhum, Phường Hắc Dịch, Thị xã Phú Mỹ, Bà Rịa - Vũng Tàu",
        "LoaiHinhDat": "Đất thổ cư",
        "DienTichDat": "255 m²",
        "Gia/M2": "4,82 triệu/m²",
        "GiayToPhapLy": "Đã có sổ",
        "DacDiemNha/Dat": "Mặt tiền\nThổ cư 1 phần",
        "ChieuNgang": "5 m",
        "ChieuDai": "51 m",
        "DonVi(M2/Hecta)": "m²"
    },
    {
        "DiaChi": "Đường Lạc Long Quân, Thị trấn Phước Hải, Huyện Đất Đỏ, Bà Rịa - Vũng Tàu",
        "LoaiHinhDat": "Đất thổ cư",
        "DienTichDat": "83 m²",
        "Gia/M2": "37,35 triệu/m²",
        "GiayToPhapLy": "Đã có sổ",
        "DacDiemNha/Dat": "Mặt tiền",
        "ChieuNgang": "6 m",
        "ChieuDai": "14 m",
        "DonVi(M2/Hecta)": "m²"
    },
    {
        "DiaChi": "Thạnh Lộc 37, Phường Thạnh Lộc, Quận 12, Tp Hồ Chí Minh",
        "LoaiHinhDat": "Đất thổ cư",
        "DienTichDat": "135 m²",
        "Gia/M2": "35,19 triệu/m²",
        "GiayToPhapLy": "Đã có sổ",
        "DacDiemNha/Dat": "Hẻm xe hơi",
        "ChieuNgang": "5 m",
        "ChieuDai": "27 m",
        "DonVi(M2/Hecta)": "m²"
    },
    {
        "DiaChi": "1A, Xã Hòa Châu, Huyện Hòa Vang, Đà Nẵng",
        "LoaiHinhDat": "Đất thổ cư",
        "DienTichDat": "120 m²",
        "Gia/M2": "12,92 triệu/m²",
        "GiayToPhapLy": "Đã có sổ",
        "DacDiemNha/Dat": "Mặt tiền",
        "ChieuNgang": "5 m",
        "ChieuDai": "24 m",
        "DonVi(M2/Hecta)": "m²"
    },
    {
        "DiaChi": "đường số 15, Xã Minh Hưng, Huyện Chơn Thành, Bình Phước",
        "LoaiHinhDat": "Đất thổ cư",
        "DienTichDat": "267 m²",
        "Gia/M2": "1,87 triệu/m²",
        "GiayToPhapLy": "Đã có sổ",
        "DacDiemNha/Dat": "Mặt tiền",
        "ChieuNgang": "5 m",
        "ChieuDai": "54 m",
        "DonVi(M2/Hecta)": "m²"
    },
    {
        "DiaChi": "Đường số 7, Phường Tam Bình (Quận Thủ Đức cũ), Thành phố Thủ Đức, Tp Hồ Chí Minh",
        "LoaiHinhDat": "Đất thổ cư",
        "DienTichDat": "100 m²",
        "Gia/M2": "89 triệu/m²",
        "GiayToPhapLy": "Đã có sổ",
        "HuongDat": "Đông Nam",
        "DacDiemNha/Dat": "Mặt tiền\nThổ cư toàn bộ",
        "ChieuNgang": "5 m",
        "ChieuDai": "20 m",
        "DonVi(M2/Hecta)": "m²"
    },
    {
        "DiaChi": "Đường Lê Văn Lương, Xã Phước Kiển, Huyện Nhà Bè, Tp Hồ Chí Minh",
        "LoaiHinhDat": "Đất thổ cư",
        "DienTichDat": "132.5 m²",
        "Gia/M2": "35,09 triệu/m²",
        "GiayToPhapLy": "Đã có sổ"
    },
    {
        "DiaChi": "Đường số 17, Phường Hiệp Bình Phước (Quận Thủ Đức cũ), Thành phố Thủ Đức, Tp Hồ Chí Minh",
        "LoaiHinhDat": "Đất thổ cư",
        "DienTichDat": "1753 m²",
        "Gia/M2": "35,37 triệu/m²",
        "GiayToPhapLy": "Đã có sổ",
        "DacDiemNha/Dat": "Hẻm xe hơi\nMặt tiền",
        "ChieuNgang": "28 m",
        "ChieuDai": "64 m"
    },
    {
        "DiaChi": "Đường Nguyễn Bình, Xã Nhơn Đức, Huyện Nhà Bè, Tp Hồ Chí Minh",
        "LoaiHinhDat": "Đất thổ cư",
        "DienTichDat": "82.5 m²",
        "Gia/M2": "44,24 triệu/m²",
        "GiayToPhapLy": "Đã có sổ",
        "ChieuNgang": "6 m",
        "ChieuDai": "13.5 m"
    },
    {
        "DiaChi": "268, Đường huyện lộ 65, Xã Bình Phú, Huyện Cai Lậy, Tiền Giang",
        "LoaiHinhDat": "Đất nông nghiệp",
        "DienTichDat": "150 m²",
        "Gia/M2": "2,80 triệu/m²",
        "GiayToPhapLy": "Đã có sổ",
        "HuongDat": "Đông Bắc",
        "DacDiemNha/Dat": "Mặt tiền\nNở hậu",
        "ChieuNgang": "5 m",
        "ChieuDai": "30 m",
        "DonVi(M2/Hecta)": "m²"
    },
    {
        "DiaChi": "Đường Lê Văn Lương, Xã Phước Kiển, Huyện Nhà Bè, Tp Hồ Chí Minh",
        "LoaiHinhDat": "Đất thổ cư",
        "DienTichDat": "102 m²",
        "Gia/M2": "56,86 triệu/m²",
        "GiayToPhapLy": "Đã có sổ",
        "ChieuNgang": "5 m",
        "ChieuDai": "21 m"
    },
    {
        "DiaChi": "Võ Nguyên Giáp, Xã Diên An, Huyện Diên Khánh, Khánh Hòa",
        "LoaiHinhDat": "Đất thổ cư",
        "DienTichDat": "1479.9 m²",
        "Gia/M2": "979.795 đ/m²",
        "GiayToPhapLy": "Đã có sổ",
        "DacDiemNha/Dat": "Hẻm xe hơi",
        "ChieuNgang": "70 m",
        "ChieuDai": "21 m"
    },
    {
        "DiaChi": "Đường Lê Văn Lương, Xã Nhơn Đức, Huyện Nhà Bè, Tp Hồ Chí Minh",
        "LoaiHinhDat": "Đất thổ cư",
        "DienTichDat": "93.6 m²",
        "Gia/M2": "40,60 triệu/m²",
        "GiayToPhapLy": "Đã có sổ",
        "ChieuNgang": "5.2 m",
        "ChieuDai": "18 m"
    },
    {
        "DiaChi": "Nguyễn Thị Định, Phường Cát Lái (Quận 2 cũ), Thành phố Thủ Đức, Tp Hồ Chí Minh",
        "LoaiHinhDat": "Đất nền dự án",
        "DienTichDat": "119 m²",
        "Gia/M2": "72 triệu/m²",
        "GiayToPhapLy": "Đang chờ sổ",
        "ChieuNgang": "7 m",
        "ChieuDai": "17 m",
        "DonVi(M2/Hecta)": "m²"
    },
    {
        "DiaChi": "Đường Lê Văn Lương, Xã Phước Kiển, Huyện Nhà Bè, Tp Hồ Chí Minh",
        "LoaiHinhDat": "Đất thổ cư",
        "DienTichDat": "170 m²",
        "Gia/M2": "56,76 triệu/m²",
        "GiayToPhapLy": "Đã có sổ",
        "ChieuNgang": "8.5 m",
        "ChieuDai": "20 m"
    },
    {
        "DiaChi": "Đường Lê Văn Lương, Xã Phước Kiển, Huyện Nhà Bè, Tp Hồ Chí Minh",
        "LoaiHinhDat": "Đất thổ cư",
        "DienTichDat": "106 m²",
        "Gia/M2": "63,21 triệu/m²",
        "GiayToPhapLy": "Đã có sổ",
        "ChieuNgang": "5 m",
        "ChieuDai": "21 m"
    },
    {
        "DiaChi": "Đường Số 4, Xã Bạch Đằng, Thị xã Tân Uyên, Bình Dương",
        "LoaiHinhDat": "Đất thổ cư",
        "DienTichDat": "516 m²",
        "Gia/M2": "5,81 triệu/m²",
        "GiayToPhapLy": "Đã có sổ",
        "HuongDat": "Đông",
        "DacDiemNha/Dat": "Thổ cư 1 phần"
    },
    {
        "DiaChi": "Đường Y Wang, Xã Ea Kao, Thành phố Buôn Ma Thuột, Đắk Lắk",
        "LoaiHinhDat": "Đất thổ cư",
        "DienTichDat": "277 m²",
        "Gia/M2": "2,04 triệu/m²",
        "GiayToPhapLy": "Đã có sổ",
        "HuongDat": "Đông Nam",
        "DacDiemNha/Dat": "Mặt tiền\nThổ cư 1 phần",
        "ChieuNgang": "5 m",
        "ChieuDai": "58 m",
        "DonVi(M2/Hecta)": "m²"
    },
    {
        "DiaChi": "Ấp Mỹ Thị A, Xã Mỹ Trung, Huyện Cái Bè, Tiền Giang",
        "LoaiHinhDat": "Đất thổ cư",
        "DienTichDat": "110 m²",
        "Gia/M2": "4,36 triệu/m²",
        "GiayToPhapLy": "Đã có sổ",
        "DacDiemNha/Dat": "Thổ cư toàn bộ",
        "ChieuNgang": "5 m",
        "ChieuDai": "22 m"
    },
    {
        "DiaChi": "Nguyễn Thị Định, Phường Cát Lái (Quận 2 cũ), Thành phố Thủ Đức, Tp Hồ Chí Minh",
        "LoaiHinhDat": "Đất nền dự án",
        "DienTichDat": "160 m²",
        "Gia/M2": "50 triệu/m²",
        "GiayToPhapLy": "Đã có sổ",
        "ChieuNgang": "8 m",
        "ChieuDai": "20 m",
        "DonVi(M2/Hecta)": "m²"
    },
    {
        "DiaChi": "bưng môn, Xã Lộc An, Huyện Long Thành, Đồng Nai",
        "LoaiHinhDat": "Đất thổ cư",
        "DienTichDat": "235 m²",
        "Gia/M2": "19,15 triệu/m²",
        "GiayToPhapLy": "Đã có sổ",
        "DacDiemNha/Dat": "Mặt tiền\nThổ cư toàn bộ",
        "ChieuNgang": "25 m",
        "ChieuDai": "9.6 m",
        "DonVi(M2/Hecta)": "m²"
    },
    {
        "DiaChi": "Doãn Thị Lê, Xã Bình Lãng, Huyện Tân Trụ, Long An",
        "LoaiHinhDat": "Đất thổ cư",
        "DienTichDat": "210 m²",
        "Gia/M2": "1,67 triệu/m²",
        "GiayToPhapLy": "Đã có sổ",
        "DacDiemNha/Dat": "Mặt tiền",
        "ChieuNgang": "9.5 m",
        "DonVi(M2/Hecta)": "m²"
    },
    {
        "DiaChi": "Khu Dân cư, Thị trấn Bến Lức, Huyện Bến Lức, Long An",
        "LoaiHinhDat": "Đất thổ cư",
        "DienTichDat": "100 m²",
        "Gia/M2": "22 triệu/m²",
        "GiayToPhapLy": "Đã có sổ",
        "DacDiemNha/Dat": "Mặt tiền",
        "ChieuNgang": "5 m",
        "DonVi(M2/Hecta)": "m²"
    },
    {
        "DiaChi": "Tỉnh lộ 832, Xã Nhựt Chánh, Bến Lức, Long An, Xã Nhựt Chánh, Huyện Bến Lức, Long An",
        "LoaiHinhDat": "Đất thổ cư",
        "DienTichDat": "72 m²",
        "Gia/M2": "13,47 triệu/m²",
        "GiayToPhapLy": "Đã có sổ",
        "DacDiemNha/Dat": "Mặt tiền",
        "DonVi(M2/Hecta)": "m²"
    },
    {
        "DiaChi": "Đường Nguyễn Tất Thành, Phường Thanh Bình, Quận Hải Châu, Đà Nẵng",
        "LoaiHinhDat": "Đất thổ cư",
        "DienTichDat": "110.3 m²",
        "Gia/M2": "108,79 triệu/m²",
        "GiayToPhapLy": "Đã có sổ",
        "DacDiemNha/Dat": "Mặt tiền",
        "ChieuNgang": "5.07 m",
        "ChieuDai": "21.75 m",
        "DonVi(M2/Hecta)": "m²"
    },
    {
        "DiaChi": "Đường Quốc lộ 50, Xã Mỹ Lộc, Huyện Cần Giuộc, Long An",
        "LoaiHinhDat": "Đất thổ cư",
        "DienTichDat": "225 m²",
        "Gia/M2": "6,67 triệu/m²",
        "GiayToPhapLy": "Đã có sổ",
        "DacDiemNha/Dat": "Hẻm xe hơi\nMặt tiền",
        "ChieuNgang": "7.5 m",
        "ChieuDai": "30 m",
        "DonVi(M2/Hecta)": "m²"
    },
    {
        "DiaChi": "Cầu Xây 2, Phường Tân Phú (Quận 9 cũ), Thành phố Thủ Đức, Tp Hồ Chí Minh",
        "LoaiHinhDat": "Đất thổ cư",
        "DienTichDat": "117 m²",
        "Gia/M2": "53,85 triệu/m²",
        "GiayToPhapLy": "Đã có sổ",
        "DacDiemNha/Dat": "Hẻm xe hơi",
        "ChieuNgang": "5.5 m",
        "ChieuDai": "22 m"
    },
    {
        "DiaChi": "Nguyễn Thị Định, Phường Cát Lái (Quận 2 cũ), Thành phố Thủ Đức, Tp Hồ Chí Minh",
        "LoaiHinhDat": "Đất nền dự án",
        "DienTichDat": "100 m²",
        "Gia/M2": "58 triệu/m²",
        "GiayToPhapLy": "Đã có sổ",
        "ChieuNgang": "5 m",
        "ChieuDai": "20 m",
        "DonVi(M2/Hecta)": "m²"
    },
    {
        "DiaChi": "Đường Bàu Công, Xã Tân Mỹ, Huyện Đức Hòa, Long An",
        "LoaiHinhDat": "Đất thổ cư",
        "DienTichDat": "3003 m²",
        "Gia/M2": "1,17 triệu/m²",
        "GiayToPhapLy": "Đã có sổ",
        "ChieuNgang": "91 m",
        "ChieuDai": "33 m"
    },
    {
        "DiaChi": "Đường Giồng Cát, Xã Tân Phú Trung, Huyện Củ Chi, Tp Hồ Chí Minh",
        "LoaiHinhDat": "Đất thổ cư",
        "DienTichDat": "180 m²",
        "Gia/M2": "9,17 triệu/m²",
        "GiayToPhapLy": "Đã có sổ",
        "ChieuNgang": "6 m",
        "ChieuDai": "30 m",
        "DonVi(M2/Hecta)": "m²"
    },
    {
        "DiaChi": "Đường Quốc lộ 20, Xã Xuân Trường, Thành phố Đà Lạt, Lâm Đồng",
        "LoaiHinhDat": "Đất nông nghiệp",
        "DienTichDat": "5000 m²",
        "Gia/M2": "135.800 đ/m²",
        "GiayToPhapLy": "Đã có sổ",
        "ChieuNgang": "100 m",
        "ChieuDai": "50 m"
    },
    {
        "DiaChi": "Giồng Lớn, Xã Mỹ Hạnh Nam, Huyện Đức Hòa, Long An",
        "LoaiHinhDat": "Đất thổ cư",
        "DienTichDat": "182 m²",
        "Gia/M2": "4,95 triệu/m²",
        "GiayToPhapLy": "Đã có sổ",
        "DacDiemNha/Dat": "Mặt tiền\nThổ cư toàn bộ\nKhông có thổ cư",
        "ChieuNgang": "5 m",
        "ChieuDai": "37 m",
        "DonVi(M2/Hecta)": "m²"
    },
    {
        "DiaChi": "Tỉnh lộ 9, Xã Mỹ Hạnh Bắc, Huyện Đức Hòa, Long An",
        "LoaiHinhDat": "Đất thổ cư",
        "DienTichDat": "112 m²",
        "Gia/M2": "15,62 triệu/m²",
        "GiayToPhapLy": "Đã có sổ",
        "HuongDat": "Nam",
        "DacDiemNha/Dat": "Hẻm xe hơi\nThổ cư toàn bộ",
        "ChieuNgang": "5 m",
        "ChieuDai": "22 m",
        "DonVi(M2/Hecta)": "m²"
    },
    {
        "DiaChi": "Hẻm 28 Đường Đào Tống Nguyên, Xã Phú Xuân, Huyện Nhà Bè, Tp Hồ Chí Minh",
        "LoaiHinhDat": "Đất thổ cư",
        "DienTichDat": "140 m²",
        "Gia/M2": "46,43 triệu/m²",
        "GiayToPhapLy": "Đã có sổ",
        "DacDiemNha/Dat": "Hẻm xe hơi",
        "ChieuNgang": "7 m",
        "ChieuDai": "20 m"
    },
    {
        "DiaChi": "Đường Số 37, Phường Tân Quy, Quận 7, Tp Hồ Chí Minh",
        "LoaiHinhDat": "Đất thổ cư",
        "DienTichDat": "72 m²",
        "Gia/M2": "133,33 triệu/m²",
        "GiayToPhapLy": "Đã có sổ",
        "ChieuNgang": "4 m",
        "ChieuDai": "18 m"
    },
    {
        "DiaChi": "Nguyễn Thị Định, Phường Cát Lái (Quận 2 cũ), Thành phố Thủ Đức, Tp Hồ Chí Minh",
        "LoaiHinhDat": "Đất nền dự án",
        "DienTichDat": "119 m²",
        "Gia/M2": "54,62 triệu/m²",
        "GiayToPhapLy": "Đang chờ sổ",
        "ChieuNgang": "7 m",
        "ChieuDai": "17 m",
        "DonVi(M2/Hecta)": "m²"
    },
    {
        "DiaChi": "Dân sinh, Thị trấn Quang Minh, Huyện Mê Linh, Hà Nội",
        "LoaiHinhDat": "Đất thổ cư",
        "DienTichDat": "57 m²",
        "Gia/M2": "54,39 triệu/m²",
        "GiayToPhapLy": "Đã có sổ",
        "HuongDat": "Đông Nam",
        "DacDiemNha/Dat": "Mặt tiền\nHẻm xe hơi\nThổ cư toàn bộ",
        "ChieuNgang": "4.5 m",
        "ChieuDai": "13 m"
    },
    {
        "DiaChi": "Đường Huỳnh Tấn Phát, Xã Phú Xuân, Huyện Nhà Bè, Tp Hồ Chí Minh",
        "LoaiHinhDat": "Đất thổ cư",
        "DienTichDat": "90 m²",
        "Gia/M2": "30,56 triệu/m²",
        "GiayToPhapLy": "Đã có sổ",
        "ChieuNgang": "5 m",
        "ChieuDai": "18 m",
        "DonVi(M2/Hecta)": "m²"
    },
    {
        "DiaChi": "Đường Võ Thị Sáu, Phường Đông Hòa, Thành phố Dĩ An, Bình Dương",
        "LoaiHinhDat": "Đất thổ cư",
        "DienTichDat": "118.5 m²",
        "Gia/M2": "54,85 triệu/m²",
        "GiayToPhapLy": "Đã có sổ",
        "DacDiemNha/Dat": "Mặt tiền",
        "ChieuNgang": "4.5 m",
        "ChieuDai": "26.35 m",
        "DonVi(M2/Hecta)": "m²"
    },
    {
        "DiaChi": "13, quốc lộ, Xã Long Tân, Huyện Dầu Tiếng, Bình Dương",
        "LoaiHinhDat": "Đất thổ cư",
        "DienTichDat": "500 m²",
        "Gia/M2": "1,90 triệu/m²",
        "GiayToPhapLy": "Đã có sổ",
        "DacDiemNha/Dat": "Mặt tiền\nNở hậu\nThổ cư 1 phần",
        "ChieuNgang": "10 m",
        "ChieuDai": "50 m",
        "DonVi(M2/Hecta)": "m²"
    },
    {
        "DiaChi": "68, Đường Lệ Chi, Xã Lệ Chi, Huyện Gia Lâm, Hà Nội",
        "LoaiHinhDat": "Đất thổ cư",
        "DienTichDat": "55 m²",
        "Gia/M2": "60,55 triệu/m²",
        "GiayToPhapLy": "Đã có sổ",
        "HuongDat": "Tây",
        "DacDiemNha/Dat": "Nở hậu\nThổ cư toàn bộ\nHẻm xe hơi",
        "ChieuNgang": "5 m",
        "ChieuDai": "11 m",
        "TenPhanKhu": "Sen Hồ",
        "DonVi(M2/Hecta)": "m²"
    },
    {
        "DiaChi": "Phước Trường 2, Phường Phước Mỹ, Quận Sơn Trà, Đà Nẵng",
        "LoaiHinhDat": "Đất thổ cư",
        "DienTichDat": "240 m²",
        "Gia/M2": "98,75 triệu/m²",
        "GiayToPhapLy": "Đã có sổ",
        "ChieuNgang": "10 m",
        "ChieuDai": "20 m",
        "DonVi(M2/Hecta)": "m²"
    },
    {
        "DiaChi": "Khu 4 Đường Giang Trôi , Thị trấn Trạm Trôi, Huyện Hoài Đức, Hà Nội",
        "LoaiHinhDat": "Đất thổ cư",
        "DienTichDat": "47.6 m²",
        "Gia/M2": "110,34 triệu/m²",
        "GiayToPhapLy": "Đã có sổ",
        "HuongDat": "Nam",
        "DacDiemNha/Dat": "Nở hậu",
        "ChieuNgang": "3.55 m",
        "ChieuDai": "13.6 m",
        "TenPhanKhu": "Khu 4 thị trấn Trạm Trôi"
    },
    {
        "DiaChi": "Đức hoà thượng , Xã Đức Hòa Thượng, Huyện Đức Hòa, Long An",
        "LoaiHinhDat": "Đất thổ cư",
        "DienTichDat": "200 m²",
        "Gia/M2": "22,50 triệu/m²",
        "GiayToPhapLy": "Đã có sổ",
        "DacDiemNha/Dat": "Mặt tiền",
        "ChieuNgang": "5 m",
        "ChieuDai": "40 m",
        "DonVi(M2/Hecta)": "m²"
    },
    {
        "DiaChi": "Đường Gò Cát, Phường Phú Hữu (Quận 9 cũ), Thành phố Thủ Đức, Tp Hồ Chí Minh",
        "LoaiHinhDat": "Đất thổ cư",
        "DienTichDat": "100 m²",
        "Gia/M2": "48 triệu/m²",
        "GiayToPhapLy": "Đã có sổ",
        "DacDiemNha/Dat": "Hẻm xe hơi",
        "ChieuNgang": "5 m",
        "ChieuDai": "20 m"
    },
    {
        "DiaChi": "Đường Số 23, Phường Tân Quy, Quận 7, Tp Hồ Chí Minh",
        "LoaiHinhDat": "Đất thổ cư",
        "DienTichDat": "72 m²",
        "Gia/M2": "151,39 triệu/m²",
        "GiayToPhapLy": "Đã có sổ",
        "HuongDat": "Bắc",
        "ChieuNgang": "4.5 m",
        "ChieuDai": "16 m"
    },
    {
        "DiaChi": "Đông La, Xã Lộc Đức, Huyện Bảo Lâm, Lâm Đồng",
        "LoaiHinhDat": "Đất thổ cư",
        "DienTichDat": "150 m²",
        "Gia/M2": "2,60 triệu/m²",
        "GiayToPhapLy": "Đã có sổ",
        "HuongDat": "Đông",
        "ChieuNgang": "5 m",
        "DonVi(M2/Hecta)": "m²"
    },
    {
        "DiaChi": "Đường Nguyễn Văn Dương, Xã Đức Hòa Đông, Huyện Đức Hòa, Long An",
        "LoaiHinhDat": "Đất thổ cư",
        "DienTichDat": "650 m²",
        "Gia/M2": "4 triệu/m²",
        "GiayToPhapLy": "Đã có sổ",
        "DacDiemNha/Dat": "Hẻm xe hơi",
        "ChieuNgang": "10 m",
        "ChieuDai": "65 m"
    },
    {
        "DiaChi": "Hương Lộ 11, Xã Long Thượng, Huyện Cần Giuộc, Long An",
        "LoaiHinhDat": "Đất nền dự án",
        "DienTichDat": "100 m²",
        "Gia/M2": "39,50 triệu/m²",
        "GiayToPhapLy": "Đang chờ sổ",
        "DacDiemNha/Dat": "Mặt tiền",
        "ChieuNgang": "5 m",
        "ChieuDai": "20 m",
        "TenPhanKhu": "B7"
    },
    {
        "DiaChi": "Đường Bùi Thiện Ngộ, Phường Hòa Xuân, Quận Cẩm Lệ, Đà Nẵng",
        "LoaiHinhDat": "Đất nền dự án",
        "DienTichDat": "100 m²",
        "Gia/M2": "43,50 triệu/m²",
        "GiayToPhapLy": "Đã có sổ",
        "HuongDat": "Tây Nam",
        "DacDiemNha/Dat": "Mặt tiền",
        "ChieuNgang": "5 m",
        "ChieuDai": "20 m"
    },
    {
        "DiaChi": "bưng môn, Xã Lộc An, Huyện Long Thành, Đồng Nai",
        "LoaiHinhDat": "Đất thổ cư",
        "DienTichDat": "163.7 m²",
        "Gia/M2": "13,44 triệu/m²",
        "GiayToPhapLy": "Đã có sổ",
        "DacDiemNha/Dat": "Mặt tiền",
        "ChieuNgang": "20.4 m",
        "DonVi(M2/Hecta)": "m²"
    },
    {
        "DiaChi": "Đường Thạnh Lộc 19, Phường Thạnh Lộc, Quận 12, Tp Hồ Chí Minh",
        "LoaiHinhDat": "Đất thổ cư",
        "DienTichDat": "137 m²",
        "Gia/M2": "48,18 triệu/m²",
        "GiayToPhapLy": "Đã có sổ",
        "DacDiemNha/Dat": "Hẻm xe hơi",
        "ChieuNgang": "5.7 m",
        "ChieuDai": "24 m",
        "DonVi(M2/Hecta)": "m²"
    },
    {
        "DiaChi": "Nhựa 6m, Xã Phú An, Thị xã Bến Cát, Bình Dương",
        "LoaiHinhDat": "Đất thổ cư",
        "DienTichDat": "1821 m²",
        "Gia/M2": "7,14 triệu/m²",
        "GiayToPhapLy": "Đã có sổ",
        "DacDiemNha/Dat": "Mặt tiền",
        "ChieuNgang": "31.6 m",
        "ChieuDai": "55 m"
    },
    {
        "DiaChi": "Đường Vườn Lài, Phường An Phú Đông, Quận 12, Tp Hồ Chí Minh",
        "LoaiHinhDat": "Đất thổ cư",
        "DienTichDat": "64.4 m²",
        "Gia/M2": "47,98 triệu/m²",
        "GiayToPhapLy": "Đã có sổ"
    },
    {
        "DiaChi": "Dt742, Xã Bình Mỹ, Huyện Bắc Tân Uyên, Bình Dương",
        "LoaiHinhDat": "Đất nền dự án",
        "DienTichDat": "70 m²",
        "Gia/M2": "17,86 triệu/m²",
        "GiayToPhapLy": "Đang chờ sổ",
        "HuongDat": "Tây Nam",
        "DacDiemNha/Dat": "Mặt tiền\nThổ cư toàn bộ",
        "ChieuNgang": "5 m",
        "ChieuDai": "14 m",
        "DonVi(M2/Hecta)": "m²"
    },
    {
        "DiaChi": "Đường Mai Chí Thọ, Phường Hòa Xuân, Quận Cẩm Lệ, Đà Nẵng",
        "LoaiHinhDat": "Đất nền dự án",
        "DienTichDat": "100 m²",
        "Gia/M2": "59 triệu/m²",
        "GiayToPhapLy": "Đã có sổ",
        "DacDiemNha/Dat": "Mặt tiền",
        "ChieuNgang": "5 m",
        "ChieuDai": "20 m"
    },
    {
        "DiaChi": "Đường đan 3m, Xã Bình Hàng Trung, Huyện Cao Lãnh, Đồng Tháp",
        "LoaiHinhDat": "Đất thổ cư",
        "DienTichDat": "225 m²",
        "Gia/M2": "2 triệu/m²",
        "GiayToPhapLy": "Đang chờ sổ",
        "DacDiemNha/Dat": "Mặt tiền",
        "ChieuNgang": "5 m",
        "ChieuDai": "45 m",
        "DonVi(M2/Hecta)": "m²"
    },
    {
        "DiaChi": "Đường Lê Đình Chi, Xã Lê Minh Xuân, Huyện Bình Chánh, Tp Hồ Chí Minh",
        "LoaiHinhDat": "Đất thổ cư",
        "DienTichDat": "246 m²",
        "Gia/M2": "14,63 triệu/m²",
        "GiayToPhapLy": "Đã có sổ",
        "DacDiemNha/Dat": "Mặt tiền",
        "ChieuNgang": "4.2 m",
        "ChieuDai": "58 m",
        "DonVi(M2/Hecta)": "m²"
    },
    {
        "DiaChi": "Đường Lê Văn Lương, Xã Phước Kiển, Huyện Nhà Bè, Tp Hồ Chí Minh",
        "LoaiHinhDat": "Đất thổ cư",
        "DienTichDat": "97 m²",
        "Gia/M2": "37,11 triệu/m²",
        "GiayToPhapLy": "Đã có sổ",
        "DacDiemNha/Dat": "Thổ cư toàn bộ",
        "ChieuNgang": "6 m",
        "ChieuDai": "16.5 m"
    },
    {
        "DiaChi": "Đường Thuận Giao 19, Phường Thuận Giao, Thành phố Thuận An, Bình Dương",
        "LoaiHinhDat": "Đất thổ cư",
        "DienTichDat": "110 m²",
        "Gia/M2": "25 triệu/m²",
        "GiayToPhapLy": "Đã có sổ",
        "ChieuNgang": "5 m",
        "ChieuDai": "22 m"
    },
    {
        "DiaChi": "Đường Tỉnh lộ 9, Xã Mỹ Hạnh Nam, Huyện Đức Hòa, Tỉnh Long An, Xã Mỹ Hạnh Nam, Huyện Đức Hòa, Long An",
        "LoaiHinhDat": "Đất thổ cư",
        "DienTichDat": "85 m²",
        "Gia/M2": "15,88 triệu/m²",
        "GiayToPhapLy": "Đã có sổ",
        "DacDiemNha/Dat": "Mặt tiền\nThổ cư toàn bộ",
        "ChieuNgang": "5 m",
        "ChieuDai": "17 m",
        "DonVi(M2/Hecta)": "m²"
    },
    {
        "DiaChi": "Kênh T2, Xã Tân Thành, Huyện Thủ Thừa, Long An",
        "LoaiHinhDat": "Đất nông nghiệp",
        "DienTichDat": "1066 m²",
        "Gia/M2": "769.230 đ/m²",
        "GiayToPhapLy": "Đã có sổ",
        "ChieuNgang": "20 m",
        "ChieuDai": "53 m",
        "DonVi(M2/Hecta)": "m²"
    },
    {
        "DiaChi": "Đường Quốc Lộ 51, Xã Tân Hải, Thị xã Phú Mỹ, Bà Rịa - Vũng Tàu",
        "LoaiHinhDat": "Đất thổ cư",
        "DienTichDat": "253 m²",
        "Gia/M2": "12,65 triệu/m²",
        "GiayToPhapLy": "Đã có sổ",
        "DacDiemNha/Dat": "Mặt tiền\nThổ cư 1 phần",
        "DonVi(M2/Hecta)": "m²"
    },
    {
        "DiaChi": "Đường nhựa 3.5m, Thị trấn Mỹ Thọ, Huyện Cao Lãnh, Đồng Tháp",
        "LoaiHinhDat": "Đất thổ cư",
        "DienTichDat": "170 m²",
        "Gia/M2": "3,24 triệu/m²",
        "GiayToPhapLy": "Đã có sổ",
        "DacDiemNha/Dat": "Mặt tiền\nThổ cư 1 phần",
        "ChieuNgang": "5 m",
        "ChieuDai": "34 m",
        "DonVi(M2/Hecta)": "m²"
    },
    {
        "DiaChi": "Đường Hoàng Diệu 2, Phường Linh Chiểu (Quận Thủ Đức cũ), Thành phố Thủ Đức, Tp Hồ Chí Minh",
        "LoaiHinhDat": "Đất thổ cư",
        "DienTichDat": "75 m²",
        "Gia/M2": "74,67 triệu/m²",
        "GiayToPhapLy": "Đã có sổ",
        "ChieuNgang": "4.3 m",
        "ChieuDai": "17 m",
        "DonVi(M2/Hecta)": "m²"
    },
    {
        "DiaChi": "dj10, Phường Thới Hòa, Thị xã Bến Cát, Bình Dương",
        "LoaiHinhDat": "Đất thổ cư",
        "DienTichDat": "300 m²",
        "Gia/M2": "12,17 triệu/m²",
        "GiayToPhapLy": "Đã có sổ",
        "DacDiemNha/Dat": "Mặt tiền",
        "ChieuNgang": "10 m",
        "ChieuDai": "30 m",
        "TenPhanKhu": "khu j",
        "DonVi(M2/Hecta)": "m²"
    },
    {
        "DiaChi": "Đường Võ Thị Sáu, Phường Đông Hòa, Thành phố Dĩ An, Bình Dương",
        "LoaiHinhDat": "Đất thổ cư",
        "DienTichDat": "100 m²",
        "Gia/M2": "33,50 triệu/m²",
        "GiayToPhapLy": "Đã có sổ",
        "HuongDat": "Đông Bắc",
        "DacDiemNha/Dat": "Hẻm xe hơi",
        "ChieuNgang": "6 m",
        "ChieuDai": "17 m",
        "DonVi(M2/Hecta)": "m²"
    },
    {
        "DiaChi": "Đường Chung Cư Tân Mỹ, Phường Hắc Dịch, Thị xã Phú Mỹ, Bà Rịa - Vũng Tàu",
        "LoaiHinhDat": "Đất thổ cư",
        "DienTichDat": "180 m²",
        "Gia/M2": "11,67 triệu/m²",
        "GiayToPhapLy": "Đã có sổ",
        "DacDiemNha/Dat": "Mặt tiền\nThổ cư 1 phần",
        "ChieuNgang": "5 m",
        "ChieuDai": "36 m"
    },
    {
        "DiaChi": "Nguyễn Thị Đẹp, Phường Hắc Dịch, Thị xã Phú Mỹ, Bà Rịa - Vũng Tàu",
        "LoaiHinhDat": "Đất thổ cư",
        "DienTichDat": "400 m²",
        "Gia/M2": "8,25 triệu/m²",
        "GiayToPhapLy": "Đã có sổ",
        "DacDiemNha/Dat": "Mặt tiền\nNở hậu\nThổ cư 1 phần",
        "ChieuNgang": "5.6 m",
        "ChieuDai": "29 m",
        "DonVi(M2/Hecta)": "m²"
    },
    {
        "DiaChi": "Đường Phạm Thái Bường, Xã Phước Khánh, Huyện Nhơn Trạch, Đồng Nai",
        "LoaiHinhDat": "Đất thổ cư",
        "DienTichDat": "91 m²",
        "Gia/M2": "17,80 triệu/m²",
        "GiayToPhapLy": "Đã có sổ",
        "HuongDat": "Đông Bắc",
        "DacDiemNha/Dat": "Thổ cư toàn bộ\nMặt tiền",
        "ChieuNgang": "4.2 m",
        "ChieuDai": "22 m"
    },
    {
        "DiaChi": "Đường Hồ Tùng Mậu, Phường Mai Dịch, Quận Cầu Giấy, Hà Nội",
        "LoaiHinhDat": "Đất thổ cư",
        "DienTichDat": "54 m²",
        "Gia/M2": "120,37 triệu/m²",
        "GiayToPhapLy": "Đã có sổ",
        "TenPhanKhu": "bán Đất Hồ Tùng mậu"
    },
    {
        "DiaChi": "Đường Nguyễn Xiển, Phường Long Thạnh Mỹ (Quận 9 cũ), Thành phố Thủ Đức, Tp Hồ Chí Minh",
        "LoaiHinhDat": "Đất thổ cư",
        "DienTichDat": "54 m²",
        "Gia/M2": "54,63 triệu/m²",
        "GiayToPhapLy": "Đã có sổ",
        "DacDiemNha/Dat": "Hẻm xe hơi\nThổ cư toàn bộ",
        "DonVi(M2/Hecta)": "m²"
    },
    {
        "DiaChi": "Hoàng Hà, Xã Cẩm Điền, Huyện Cẩm Giàng, Hải Dương",
        "LoaiHinhDat": "Đất thổ cư",
        "DienTichDat": "152 m²",
        "Gia/M2": "14,47 triệu/m²",
        "GiayToPhapLy": "Đã có sổ",
        "ChieuNgang": "8 m",
        "ChieuDai": "19 m",
        "TenPhanKhu": "Thửa đất số 976 diện tích 152m2",
        "DonVi(M2/Hecta)": "m²"
    },
    {
        "DiaChi": "Đường số 7, Phường Tam Bình (Quận Thủ Đức cũ), Thành phố Thủ Đức, Tp Hồ Chí Minh",
        "LoaiHinhDat": "Đất thổ cư",
        "DienTichDat": "91 m²",
        "Gia/M2": "61,54 triệu/m²",
        "GiayToPhapLy": "Đã có sổ",
        "DacDiemNha/Dat": "Hẻm xe hơi"
    },
    {
        "DiaChi": "Đê Bao Sông Sài Gòn, Phường Vĩnh Phú, Thành phố Thuận An, Bình Dương",
        "LoaiHinhDat": "Đất thổ cư",
        "DienTichDat": "1100 m²",
        "Gia/M2": "20,91 triệu/m²",
        "GiayToPhapLy": "Đã có sổ",
        "DacDiemNha/Dat": "Mặt tiền",
        "ChieuNgang": "63 m",
        "ChieuDai": "18 m",
        "DonVi(M2/Hecta)": "m²"
    },
    {
        "DiaChi": "Đường nhựa 7m, Xã Tân Hội Trung, Huyện Cao Lãnh, Đồng Tháp",
        "LoaiHinhDat": "Đất thổ cư",
        "DienTichDat": "200 m²",
        "Gia/M2": "2,50 triệu/m²",
        "GiayToPhapLy": "Đã có sổ",
        "DacDiemNha/Dat": "Mặt tiền\nThổ cư 1 phần",
        "ChieuNgang": "6 m",
        "ChieuDai": "33 m",
        "DonVi(M2/Hecta)": "m²"
    },
    {
        "DiaChi": "Đường Hoàng Diệu 2, Phường Linh Trung (Quận Thủ Đức cũ), Thành phố Thủ Đức, Tp Hồ Chí Minh",
        "LoaiHinhDat": "Đất thổ cư",
        "DienTichDat": "51 m²",
        "Gia/M2": "102,94 triệu/m²",
        "GiayToPhapLy": "Đã có sổ",
        "DacDiemNha/Dat": "Hẻm xe hơi",
        "ChieuNgang": "4.84 m",
        "ChieuDai": "10.5 m",
        "DonVi(M2/Hecta)": "m²"
    },
    {
        "DiaChi": "ĐƯỜNG LA THÀNH, Xã Tân Tiến, Huyện Chương Mỹ, Hà Nội",
        "LoaiHinhDat": "Đất thổ cư",
        "DienTichDat": "75 m²",
        "Gia/M2": "22,67 triệu/m²",
        "GiayToPhapLy": "Đã có sổ",
        "DacDiemNha/Dat": "Thổ cư toàn bộ",
        "ChieuNgang": "5 m",
        "ChieuDai": "15 m",
        "DonVi(M2/Hecta)": "m²"
    },
    {
        "DiaChi": "Đường nhựa 3.5m, Xã Bình Hàng Tây, Huyện Cao Lãnh, Đồng Tháp",
        "LoaiHinhDat": "Đất thổ cư",
        "DienTichDat": "300 m²",
        "Gia/M2": "2,07 triệu/m²",
        "GiayToPhapLy": "Đã có sổ",
        "DacDiemNha/Dat": "Mặt tiền",
        "ChieuNgang": "10 m",
        "ChieuDai": "30 m",
        "DonVi(M2/Hecta)": "m²"
    },
    {
        "DiaChi": "Đường Lê Thị Riêng, Phường Thới An, Quận 12, Tp Hồ Chí Minh",
        "LoaiHinhDat": "Đất thổ cư",
        "DienTichDat": "200 m²",
        "Gia/M2": "55 triệu/m²",
        "GiayToPhapLy": "Đã có sổ",
        "DacDiemNha/Dat": "Mặt tiền",
        "ChieuNgang": "10 m",
        "ChieuDai": "20 m",
        "DonVi(M2/Hecta)": "m²"
    },
    {
        "DiaChi": "Đường An Khương Thới, Xã Thuận Mỹ, Huyện Châu Thành, Long An",
        "LoaiHinhDat": "Đất thổ cư",
        "DienTichDat": "200 m²",
        "Gia/M2": "5 triệu/m²",
        "GiayToPhapLy": "Đã có sổ",
        "ChieuNgang": "10 m",
        "ChieuDai": "20 m"
    },
    {
        "DiaChi": "Đường Lê Văn Lương, Xã Phước Kiển, Huyện Nhà Bè, Tp Hồ Chí Minh",
        "LoaiHinhDat": "Đất thổ cư",
        "DienTichDat": "79.56 m²",
        "Gia/M2": "43,99 triệu/m²",
        "GiayToPhapLy": "Đã có sổ",
        "DacDiemNha/Dat": "Hẻm xe hơi",
        "ChieuNgang": "7.8 m",
        "ChieuDai": "10.2 m"
    },
    {
        "DiaChi": "Đường ĐT. 816, Xã Bình Đức, Huyện Bến Lức, Long An",
        "LoaiHinhDat": "Đất nông nghiệp",
        "DienTichDat": "1100 m²",
        "Gia/M2": "1,36 triệu/m²",
        "GiayToPhapLy": "Đã có sổ",
        "ChieuNgang": "16.85 m",
        "ChieuDai": "65.6 m"
    },
    {
        "DiaChi": "Đường ĐT. 816, Xã Bình Đức, Huyện Bến Lức, Long An",
        "LoaiHinhDat": "Đất nông nghiệp",
        "DienTichDat": "1000 m²",
        "Gia/M2": "700.000 đ/m²",
        "GiayToPhapLy": "Đã có sổ",
        "ChieuNgang": "12.5 m",
        "ChieuDai": "78 m"
    },
    {
        "DiaChi": "Đường nhựa xe 3.5m, Xã Tân Hội Trung, Huyện Cao Lãnh, Đồng Tháp",
        "LoaiHinhDat": "Đất nông nghiệp",
        "DienTichDat": "6500 m²",
        "Gia/M2": "215.000 đ/m²",
        "GiayToPhapLy": "Đã có sổ",
        "DacDiemNha/Dat": "Mặt tiền\nKhông có thổ cư",
        "ChieuNgang": "17 m",
        "ChieuDai": "382 m",
        "DonVi(M2/Hecta)": "m²"
    },
    {
        "DiaChi": "Đường Quốc lộ 22, Xã Tân Thới Nhì, Huyện Hóc Môn, Tp Hồ Chí Minh",
        "LoaiHinhDat": "Đất nông nghiệp",
        "DienTichDat": "6400 m²",
        "Gia/M2": "500 đ/m²",
        "GiayToPhapLy": "Đã có sổ",
        "HuongDat": "Đông",
        "DacDiemNha/Dat": "Mặt tiền",
        "ChieuNgang": "70 m",
        "ChieuDai": "91 m"
    },
    {
        "DiaChi": "Đường Tân Phước Khánh 30, Phường Tân Phước Khánh, Thị xã Tân Uyên, Bình Dương",
        "LoaiHinhDat": "Đất thổ cư",
        "DienTichDat": "155 m²",
        "Gia/M2": "10,26 triệu/m²",
        "GiayToPhapLy": "Đã có sổ",
        "ChieuNgang": "5 m",
        "ChieuDai": "31 m"
    },
    {
        "DiaChi": "Đường Bưng Ông Thoàn, Phường Phú Hữu (Quận 9 cũ), Thành phố Thủ Đức, Tp Hồ Chí Minh",
        "LoaiHinhDat": "Đất thổ cư",
        "DienTichDat": "170 m²",
        "Gia/M2": "40,59 triệu/m²",
        "GiayToPhapLy": "Đã có sổ",
        "DacDiemNha/Dat": "Hẻm xe hơi\nThổ cư toàn bộ",
        "ChieuNgang": "5 m",
        "ChieuDai": "34 m",
        "DonVi(M2/Hecta)": "m²"
    },
    {
        "DiaChi": "Đường Tiền Lân 17, Xã Bà Điểm, Huyện Hóc Môn, Tp Hồ Chí Minh",
        "LoaiHinhDat": "Đất thổ cư",
        "DienTichDat": "130 m²",
        "Gia/M2": "35,31 triệu/m²",
        "GiayToPhapLy": "Đã có sổ",
        "HuongDat": "Tây Nam",
        "DacDiemNha/Dat": "Thổ cư toàn bộ",
        "ChieuNgang": "5 m",
        "ChieuDai": "26 m"
    },
    {
        "DiaChi": "Đường Dương Lâm, Phường Nại Hiên Đông, Quận Sơn Trà, Đà Nẵng",
        "LoaiHinhDat": "Đất thổ cư",
        "DienTichDat": "171 m²",
        "Gia/M2": "46,49 triệu/m²",
        "GiayToPhapLy": "Đã có sổ",
        "HuongDat": "Đông Bắc",
        "DacDiemNha/Dat": "Mặt tiền",
        "ChieuNgang": "7 m",
        "ChieuDai": "24.5 m",
        "DonVi(M2/Hecta)": "m²"
    },
    {
        "DiaChi": "Đường Võ Văn Vân, Xã Vĩnh Lộc B, Huyện Bình Chánh, Tp Hồ Chí Minh",
        "LoaiHinhDat": "Đất thổ cư",
        "DienTichDat": "1282 m²",
        "Gia/M2": "27,85 triệu/m²",
        "GiayToPhapLy": "Đã có sổ",
        "HuongDat": "Đông",
        "DacDiemNha/Dat": "Mặt tiền\nHẻm xe hơi\nThổ cư toàn bộ",
        "ChieuNgang": "20 m",
        "ChieuDai": "65 m",
        "DonVi(M2/Hecta)": "m²"
    },
    {
        "DiaChi": "1234, Tàu Kem, Xã Phú Túc, Huyện Định Quán, Đồng Nai",
        "LoaiHinhDat": "Đất thổ cư",
        "DienTichDat": "430 m²",
        "Gia/M2": "883.720 đ/m²",
        "GiayToPhapLy": "Đã có sổ",
        "HuongDat": "Đông Nam",
        "DacDiemNha/Dat": "Mặt tiền\nNở hậu",
        "ChieuNgang": "10 m",
        "ChieuDai": "43 m",
        "DonVi(M2/Hecta)": "m²"
    },
    {
        "DiaChi": "Đường Nguyễn Văn Tạo, Xã Long Thới, Huyện Nhà Bè, Tp Hồ Chí Minh",
        "LoaiHinhDat": "Đất thổ cư",
        "DienTichDat": "160 m²",
        "Gia/M2": "28,75 triệu/m²",
        "GiayToPhapLy": "Đã có sổ",
        "DacDiemNha/Dat": "Hẻm xe hơi",
        "ChieuNgang": "8 m",
        "ChieuDai": "20 m",
        "DonVi(M2/Hecta)": "m²"
    },
    {
        "DiaChi": "Đường Bình Kỳ, Phường Hoà Quý, Quận Ngũ Hành Sơn, Đà Nẵng",
        "LoaiHinhDat": "Đất thổ cư",
        "DienTichDat": "97 m²",
        "Gia/M2": "23,20 triệu/m²",
        "GiayToPhapLy": "Đã có sổ",
        "HuongDat": "Tây Nam",
        "ChieuNgang": "6.5 m"
    },
    {
        "DiaChi": "Đường Kiều Phụng, Phường Hòa Xuân, Quận Cẩm Lệ, Đà Nẵng",
        "LoaiHinhDat": "Đất thổ cư",
        "DienTichDat": "100 m²",
        "Gia/M2": "35 triệu/m²",
        "GiayToPhapLy": "Đã có sổ",
        "HuongDat": "Đông",
        "DacDiemNha/Dat": "Mặt tiền",
        "ChieuNgang": "5 m",
        "ChieuDai": "20 m",
        "DonVi(M2/Hecta)": "m²"
    },
    {
        "DiaChi": "DT610b, Xã Điện Quang, Thị xã Điện Bàn, Quảng Nam",
        "LoaiHinhDat": "Đất thổ cư",
        "DienTichDat": "100 m²",
        "Gia/M2": "5 triệu/m²",
        "GiayToPhapLy": "Đã có sổ",
        "DacDiemNha/Dat": "Mặt tiền\nThổ cư toàn bộ",
        "ChieuNgang": "5 m",
        "ChieuDai": "20 m"
    },
    {
        "DiaChi": "KDC TT Mỹ Thọ, Thị trấn Mỹ Thọ, Huyện Cao Lãnh, Đồng Tháp",
        "LoaiHinhDat": "Đất thổ cư",
        "DienTichDat": "83 m²",
        "Gia/M2": "9,88 triệu/m²",
        "GiayToPhapLy": "Đã có sổ",
        "DacDiemNha/Dat": "Mặt tiền\nThổ cư toàn bộ",
        "ChieuNgang": "4.5 m",
        "ChieuDai": "18.5 m",
        "DonVi(M2/Hecta)": "m²"
    },
    {
        "DiaChi": "Khu Dân Cư Hiệp Bình, Xã Hòa Thạnh, Huyện Châu Thành, Tây Ninh",
        "LoaiHinhDat": "Đất thổ cư",
        "DienTichDat": "1016 m²",
        "Gia/M2": "738.188 đ/m²",
        "GiayToPhapLy": "Đã có sổ",
        "DacDiemNha/Dat": "Mặt tiền\nHẻm xe hơi\nNở hậu\nThổ cư 1 phần",
        "ChieuNgang": "10.5 m",
        "ChieuDai": "97 m",
        "DonVi(M2/Hecta)": "m²"
    },
    {
        "DiaChi": "56B, Thị trấn Ngãi Giao, Huyện Châu Đức, Bà Rịa - Vũng Tàu",
        "LoaiHinhDat": "Đất thổ cư",
        "DienTichDat": "188 m²",
        "Gia/M2": "6,12 triệu/m²",
        "GiayToPhapLy": "Đã có sổ",
        "HuongDat": "Tây Bắc",
        "ChieuNgang": "7 m",
        "ChieuDai": "27 m",
        "DonVi(M2/Hecta)": "m²"
    },
    {
        "DiaChi": "Đường số 6, Phường Long Trường (Quận 9 cũ), Thành phố Thủ Đức, Tp Hồ Chí Minh",
        "LoaiHinhDat": "Đất thổ cư",
        "DienTichDat": "75 m²",
        "Gia/M2": "36,67 triệu/m²",
        "GiayToPhapLy": "Đã có sổ",
        "ChieuNgang": "5 m",
        "ChieuDai": "15 m",
        "DonVi(M2/Hecta)": "m²"
    },
    {
        "DiaChi": "Đường Liên Xã Thị Trấn Tân Hiệp, Thị trấn Hóc Môn, Huyện Hóc Môn, Tp Hồ Chí Minh",
        "LoaiHinhDat": "Đất thổ cư",
        "DienTichDat": "140 m²",
        "Gia/M2": "28,21 triệu/m²",
        "GiayToPhapLy": "Đã có sổ",
        "DacDiemNha/Dat": "Hẻm xe hơi\nThổ cư toàn bộ",
        "DonVi(M2/Hecta)": "m²"
    },
    {
        "DiaChi": "Đường An Phú, Phường An Phú Đông, Quận 12, Tp Hồ Chí Minh",
        "LoaiHinhDat": "Đất thổ cư",
        "DienTichDat": "51 m²",
        "Gia/M2": "75,49 triệu/m²",
        "GiayToPhapLy": "Đã có sổ",
        "DacDiemNha/Dat": "Hẻm xe hơi"
    },
    {
        "DiaChi": "Đường Nguyễn Văn Linh, Phường Long Hòa, Quận Bình Thuỷ, Cần Thơ",
        "LoaiHinhDat": "Đất thổ cư",
        "DienTichDat": "60 m²",
        "Gia/M2": "12,50 triệu/m²",
        "GiayToPhapLy": "Đã có sổ"
    },
    {
        "DiaChi": "Lê Tấn Trung, Phường Mân Thái, Quận Sơn Trà, Đà Nẵng",
        "LoaiHinhDat": "Đất thổ cư",
        "DienTichDat": "151 m²",
        "Gia/M2": "22,52 triệu/m²",
        "GiayToPhapLy": "Đã có sổ",
        "HuongDat": "Đông Nam",
        "DacDiemNha/Dat": "Nở hậu\nThổ cư 1 phần",
        "ChieuNgang": "6.5 m",
        "DonVi(M2/Hecta)": "m²"
    },
    {
        "DiaChi": "339, Phường Phước Long B (Quận 9 cũ), Thành phố Thủ Đức, Tp Hồ Chí Minh",
        "LoaiHinhDat": "Đất thổ cư",
        "DienTichDat": "70 m²",
        "Gia/M2": "63,57 triệu/m²",
        "GiayToPhapLy": "Đã có sổ",
        "DacDiemNha/Dat": "Hẻm xe hơi",
        "ChieuNgang": "4.5 m",
        "ChieuDai": "15.5 m"
    },
    {
        "DiaChi": "Đường Thạnh Xuân 33, Phường Thạnh Xuân, Quận 12, Tp Hồ Chí Minh",
        "LoaiHinhDat": "Đất thổ cư",
        "DienTichDat": "157 m²",
        "Gia/M2": "30,25 triệu/m²",
        "GiayToPhapLy": "Đã có sổ",
        "HuongDat": "Tây",
        "DacDiemNha/Dat": "Mặt tiền\nHẻm xe hơi",
        "ChieuNgang": "5 m",
        "ChieuDai": "31 m",
        "DonVi(M2/Hecta)": "m²"
    },
    {
        "DiaChi": "dầu ba, Xã An Phước, Huyện Long Thành, Đồng Nai",
        "LoaiHinhDat": "Đất thổ cư",
        "DienTichDat": "1042 m²",
        "Gia/M2": "14,88 triệu/m²",
        "GiayToPhapLy": "Đã có sổ",
        "DacDiemNha/Dat": "Mặt tiền\nThổ cư 1 phần",
        "ChieuNgang": "23 m",
        "ChieuDai": "38.8 m",
        "DonVi(M2/Hecta)": "m²"
    },
    {
        "DiaChi": "A3, Phường Hưng Phú, Quận Cái Răng, Cần Thơ",
        "LoaiHinhDat": "Đất nền dự án",
        "DienTichDat": "120 m²",
        "Gia/M2": "25 triệu/m²",
        "GiayToPhapLy": "Đã có sổ",
        "HuongDat": "Tây Bắc"
    },
    {
        "DiaChi": "Liên xã, Xã Phước Thể, Huyện Tuy Phong, Bình Thuận",
        "LoaiHinhDat": "Đất thổ cư",
        "DienTichDat": "200 m²",
        "Gia/M2": "6 triệu/m²",
        "GiayToPhapLy": "Đã có sổ",
        "DacDiemNha/Dat": "Mặt tiền",
        "DonVi(M2/Hecta)": "m²"
    },
    {
        "DiaChi": "Đường số 22, Phường Long Thạnh Mỹ (Quận 9 cũ), Thành phố Thủ Đức, Tp Hồ Chí Minh",
        "LoaiHinhDat": "Đất nông nghiệp",
        "DienTichDat": "580 m²",
        "Gia/M2": "17,24 triệu/m²",
        "GiayToPhapLy": "Đã có sổ",
        "DacDiemNha/Dat": "Hẻm xe hơi",
        "ChieuNgang": "32 m",
        "DonVi(M2/Hecta)": "m²"
    },
    {
        "DiaChi": "44, Đường Trần Văn Sắc, Phường Thảo Điền (Quận 2 cũ), Thành phố Thủ Đức, Tp Hồ Chí Minh",
        "LoaiHinhDat": "Đất thổ cư",
        "DienTichDat": "250 m²",
        "Gia/M2": "232 triệu/m²",
        "GiayToPhapLy": "Đã có sổ",
        "ChieuNgang": "10 m",
        "ChieuDai": "25 m"
    },
    {
        "DiaChi": "Đường Hương Lộ 2, Phường Bình Trị Đông A, Quận Bình Tân, Tp Hồ Chí Minh",
        "LoaiHinhDat": "Đất thổ cư",
        "DienTichDat": "900 m²",
        "Gia/M2": "38,44 triệu/m²",
        "GiayToPhapLy": "Đã có sổ",
        "DacDiemNha/Dat": "Hẻm xe hơi\nNở hậu",
        "ChieuNgang": "25 m",
        "ChieuDai": "30 m",
        "DonVi(M2/Hecta)": "m²"
    },
    {
        "DiaChi": "Đường Tân Hiệp, Phường Tân Bình, Thành phố Dĩ An, Bình Dương",
        "LoaiHinhDat": "Đất thổ cư",
        "DienTichDat": "76 m²",
        "Gia/M2": "21,05 triệu/m²",
        "GiayToPhapLy": "Đã có sổ",
        "HuongDat": "Đông Nam",
        "DacDiemNha/Dat": "Thổ cư 1 phần",
        "ChieuNgang": "4.5 m",
        "ChieuDai": "16 m"
    },
    {
        "DiaChi": "Đường Tỉnh lộ 7, Xã Thái Mỹ, Huyện Củ Chi, Tp Hồ Chí Minh",
        "LoaiHinhDat": "Đất nông nghiệp",
        "DienTichDat": "1264 m²",
        "Gia/M2": "712.025 đ/m²",
        "GiayToPhapLy": "Đã có sổ",
        "HuongDat": "Đông Bắc",
        "DacDiemNha/Dat": "Không có thổ cư\nChưa có thổ cư",
        "ChieuNgang": "17 m",
        "ChieuDai": "73 m"
    },
    {
        "DiaChi": "Long Nguyên 20, Xã Long Nguyên, Huyện Bàu Bàng, Bình Dương",
        "LoaiHinhDat": "Đất thổ cư",
        "DienTichDat": "5177 m²",
        "Gia/M2": "3,19 triệu/m²",
        "GiayToPhapLy": "Đã có sổ",
        "DacDiemNha/Dat": "Mặt tiền\nHẻm xe hơi\nNở hậu",
        "ChieuNgang": "77 m",
        "ChieuDai": "93 m",
        "DonVi(M2/Hecta)": "m²"
    },
    {
        "DiaChi": null
    },
    {
        "DiaChi": "Thôn MỖ, Xã Xuân Giao, Huyện Bảo Thắng, Lào Cai",
        "LoaiHinhDat": "Đất thổ cư",
        "DienTichDat": "95 m²",
        "Gia/M2": "5,26 triệu/m²",
        "GiayToPhapLy": "Đã có sổ",
        "DacDiemNha/Dat": "Mặt tiền\nThổ cư toàn bộ",
        "DonVi(M2/Hecta)": "m²"
    },
    {
        "DiaChi": "80, Đường Dương Cát Lợi, Thị trấn Nhà Bè, Huyện Nhà Bè, Tp Hồ Chí Minh",
        "LoaiHinhDat": "Đất thổ cư",
        "DienTichDat": "51 m²",
        "Gia/M2": "70,59 triệu/m²",
        "GiayToPhapLy": "Đã có sổ",
        "HuongDat": "Đông Nam",
        "DacDiemNha/Dat": "Hẻm xe hơi",
        "ChieuNgang": "8.5 m",
        "ChieuDai": "6 m"
    },
    {
        "DiaChi": "Đường Trần Văn Quế, Phường Hòa Hiệp Nam, Quận Liên Chiểu, Đà Nẵng",
        "LoaiHinhDat": "Đất nền dự án",
        "DienTichDat": "100 m²",
        "Gia/M2": "32,50 triệu/m²",
        "GiayToPhapLy": "Đã có sổ",
        "HuongDat": "Tây Bắc",
        "DacDiemNha/Dat": "Mặt tiền",
        "ChieuNgang": "5 m",
        "ChieuDai": "20 m"
    },
    {
        "DiaChi": "Quốc Lộ 1K, Phường Đông Hòa, Thành phố Dĩ An, Bình Dương",
        "LoaiHinhDat": "Đất thổ cư",
        "DienTichDat": "150 m²",
        "Gia/M2": "22,33 triệu/m²",
        "GiayToPhapLy": "Đã có sổ",
        "HuongDat": "Bắc",
        "ChieuNgang": "4.9 m",
        "DonVi(M2/Hecta)": "m²"
    },
    {
        "DiaChi": "Tl23, Xã Kim Chung, Huyện Đông Anh, Hà Nội",
        "LoaiHinhDat": "Đất thổ cư",
        "DienTichDat": "100 m²",
        "Gia/M2": "55 triệu/m²",
        "GiayToPhapLy": "Đã có sổ",
        "DonVi(M2/Hecta)": "m²"
    },
    {
        "DiaChi": "Đường tỉnh 747, Xã Bình Mỹ, Huyện Bắc Tân Uyên, Bình Dương",
        "LoaiHinhDat": "Đất thổ cư",
        "DienTichDat": "150 m²",
        "Gia/M2": "8,73 triệu/m²",
        "GiayToPhapLy": "Đã có sổ",
        "DacDiemNha/Dat": "Mặt tiền\nThổ cư toàn bộ",
        "ChieuNgang": "5 m",
        "ChieuDai": "30 m",
        "DonVi(M2/Hecta)": "m²"
    },
    {
        "DiaChi": "Đường Đan, Xã Đức Tân, Huyện Tân Trụ, Long An",
        "LoaiHinhDat": "Đất nông nghiệp",
        "DienTichDat": "1400 m²",
        "Gia/M2": "450.000 đ/m²",
        "GiayToPhapLy": "Đã có sổ",
        "DonVi(M2/Hecta)": "m²"
    },
    {
        "DiaChi": "Đường Lê Bôi, Phường Mân Thái, Quận Sơn Trà, Đà Nẵng",
        "LoaiHinhDat": "Đất thổ cư",
        "DienTichDat": "58 m²",
        "Gia/M2": "43,10 triệu/m²",
        "GiayToPhapLy": "Đã có sổ",
        "HuongDat": "Đông Bắc",
        "DacDiemNha/Dat": "Thổ cư toàn bộ",
        "ChieuNgang": "4.5 m",
        "DonVi(M2/Hecta)": "m²"
    },
    {
        "DiaChi": "Đường Thạnh Xuân 48, Phường Thạnh Xuân, Quận 12, Tp Hồ Chí Minh",
        "LoaiHinhDat": "Đất thổ cư",
        "DienTichDat": "64 m²",
        "Gia/M2": "42,97 triệu/m²",
        "GiayToPhapLy": "Đang chờ sổ",
        "HuongDat": "Tây Bắc",
        "DacDiemNha/Dat": "Hẻm xe hơi",
        "ChieuNgang": "4 m",
        "ChieuDai": "16 m",
        "DonVi(M2/Hecta)": "m²"
    },
    {
        "DiaChi": "Đường Võ Văn Kiệt, Phường Long Hòa, Quận Bình Thuỷ, Cần Thơ",
        "LoaiHinhDat": "Đất nông nghiệp",
        "DienTichDat": "5673.5 m²",
        "Gia/M2": "2,50 triệu/m²",
        "GiayToPhapLy": "Đã có sổ",
        "HuongDat": "Đông Bắc",
        "TenPhanKhu": "Đất xây dựng kho xưởng\n nhà vườn sát bên đường Võ Văn Kiệt\n trên đất đã có nhà vườn và cây ăn trái",
        "DonVi(M2/Hecta)": "m²"
    },
    {
        "DiaChi": "Phố Chính Kinh, Phường Nhân Chính, Quận Thanh Xuân, Hà Nội",
        "LoaiHinhDat": "Đất thổ cư",
        "DienTichDat": "32 m²",
        "Gia/M2": "150 triệu/m²",
        "GiayToPhapLy": "Đã có sổ",
        "DacDiemNha/Dat": "Thổ cư toàn bộ",
        "ChieuNgang": "3.2 m",
        "ChieuDai": "10 m"
    },
    {
        "DiaChi": "Đường Suối Lội, Xã Tân Thông Hội, Huyện Củ Chi, Tp Hồ Chí Minh",
        "LoaiHinhDat": "Đất thổ cư",
        "DienTichDat": "340 m²",
        "Gia/M2": "4,12 triệu/m²",
        "GiayToPhapLy": "Đã có sổ",
        "DacDiemNha/Dat": "Mặt tiền",
        "ChieuNgang": "10 m",
        "ChieuDai": "34 m"
    },
    {
        "DiaChi": "Đường Bạch Hổ, Phường Mỹ Bình, Thành phố Long Xuyên, An Giang",
        "LoaiHinhDat": "Đất thổ cư",
        "DienTichDat": "501.1 m²",
        "Gia/M2": "45,90 triệu/m²",
        "GiayToPhapLy": "Đã có sổ",
        "DacDiemNha/Dat": "Thổ cư toàn bộ",
        "TenPhanKhu": "Đất thổ cư 501m2 trung tâm 3 trường: TNH\n ND\n CBL",
        "DonVi(M2/Hecta)": "m²"
    },
    {
        "DiaChi": "Đường Nguyễn Đức Trung, Phường Xuân Hà, Quận Thanh Khê, Đà Nẵng",
        "LoaiHinhDat": "Đất thổ cư",
        "DienTichDat": "100 m²",
        "Gia/M2": "86,80 triệu/m²",
        "GiayToPhapLy": "Đã có sổ",
        "DacDiemNha/Dat": "Mặt tiền",
        "ChieuNgang": "5 m",
        "ChieuDai": "20 m",
        "DonVi(M2/Hecta)": "m²"
    },
    {
        "DiaChi": "Đường Chuyên Dùng Chính, Phường Phú Mỹ, Quận 7, Tp Hồ Chí Minh",
        "LoaiHinhDat": "Đất thổ cư",
        "DienTichDat": "93 m²",
        "Gia/M2": "51,61 triệu/m²",
        "GiayToPhapLy": "Đã có sổ",
        "HuongDat": "Đông Nam",
        "DacDiemNha/Dat": "Mặt tiền\nHẻm xe hơi",
        "ChieuNgang": "7 m",
        "ChieuDai": "14 m",
        "DonVi(M2/Hecta)": "m²"
    },
    {
        "DiaChi": "Đường Trương Văn Bang, Thị trấn Cần Giuộc, Huyện Cần Giuộc, Long An",
        "LoaiHinhDat": "Đất thổ cư",
        "DienTichDat": "105 m²",
        "Gia/M2": "23,81 triệu/m²",
        "GiayToPhapLy": "Đã có sổ",
        "DacDiemNha/Dat": "Mặt tiền\nHẻm xe hơi\nThổ cư toàn bộ\nNở hậu",
        "DonVi(M2/Hecta)": "m²"
    },
    {
        "DiaChi": "Đường Thuận Giao 25, Phường Thuận Giao, Thành phố Thuận An, Bình Dương",
        "LoaiHinhDat": "Đất thổ cư",
        "DienTichDat": "131 m²",
        "Gia/M2": "34,35 triệu/m²",
        "GiayToPhapLy": "Đã có sổ",
        "DacDiemNha/Dat": "Mặt tiền",
        "ChieuNgang": "5 m",
        "DonVi(M2/Hecta)": "m²"
    },
    {
        "DiaChi": "Hẻm 699 Đường Võ Văn Kiêt,k3 P2,tp Sóc Trăng, Phường 2, Thành phố Sóc Trăng, Sóc Trăng",
        "LoaiHinhDat": "Đất thổ cư",
        "DienTichDat": "499 m²",
        "Gia/M2": "7,82 triệu/m²",
        "GiayToPhapLy": "Đã có sổ",
        "HuongDat": "Đông Nam",
        "DacDiemNha/Dat": "Hẻm xe hơi",
        "ChieuNgang": "15 m",
        "ChieuDai": "34 m",
        "DonVi(M2/Hecta)": "m²"
    },
    {
        "DiaChi": "TT Hành Chính, Thị trấn Dầu Tiếng, Huyện Dầu Tiếng, Bình Dương",
        "LoaiHinhDat": "Đất thổ cư",
        "DienTichDat": "2040 m²",
        "Gia/M2": "3,43 triệu/m²",
        "GiayToPhapLy": "Đã có sổ",
        "DacDiemNha/Dat": "Thổ cư 1 phần",
        "ChieuNgang": "26 m",
        "ChieuDai": "85 m"
    },
    {
        "DiaChi": "Đường tỉnh 725, Xã Mê Linh, Huyện Lâm Hà, Lâm Đồng",
        "LoaiHinhDat": "Đất thổ cư",
        "DienTichDat": "500 m²",
        "Gia/M2": "2,80 triệu/m²",
        "GiayToPhapLy": "Đã có sổ",
        "DacDiemNha/Dat": "Thổ cư 1 phần\nMặt tiền",
        "ChieuNgang": "10 m",
        "ChieuDai": "50 m"
    },
    {
        "DiaChi": "Đường Quốc lộ 1, Xã Hòa Châu, Huyện Hòa Vang, Đà Nẵng",
        "LoaiHinhDat": "Đất nền dự án",
        "DienTichDat": "150 m²",
        "Gia/M2": "17 triệu/m²",
        "GiayToPhapLy": "Đã có sổ",
        "HuongDat": "Tây",
        "DacDiemNha/Dat": "Mặt tiền\nHẻm xe hơi\nThổ cư toàn bộ",
        "ChieuNgang": "6 m",
        "ChieuDai": "25 m"
    },
    {
        "DiaChi": "Đường Hoàng Văn Thái, Phường Hòa Khánh Nam, Quận Liên Chiểu, Đà Nẵng",
        "LoaiHinhDat": "Đất thổ cư",
        "DienTichDat": "92 m²",
        "Gia/M2": "20,11 triệu/m²",
        "GiayToPhapLy": "Đã có sổ",
        "HuongDat": "Đông Nam",
        "DacDiemNha/Dat": "Hẻm xe hơi",
        "ChieuNgang": "5 m",
        "ChieuDai": "18 m",
        "DonVi(M2/Hecta)": "m²"
    },
    {
        "DiaChi": "Đường Lê Thị Hà, Xã Thới Tam Thôn, Huyện Hóc Môn, Tp Hồ Chí Minh",
        "LoaiHinhDat": "Đất thổ cư",
        "DienTichDat": "80 m²",
        "Gia/M2": "18,75 triệu/m²",
        "GiayToPhapLy": "Đã có sổ",
        "DacDiemNha/Dat": "Nở hậu\nThổ cư toàn bộ",
        "DonVi(M2/Hecta)": "m²"
    },
    {
        "DiaChi": "Đường Bành Văn Trân, Phường 7, Quận Tân Bình, Tp Hồ Chí Minh",
        "LoaiHinhDat": "Đất thổ cư",
        "DienTichDat": "44 m²",
        "Gia/M2": "156,82 triệu/m²",
        "GiayToPhapLy": "Đã có sổ",
        "DacDiemNha/Dat": "Hẻm xe hơi\nNở hậu",
        "ChieuNgang": "3.8 m",
        "ChieuDai": "12 m",
        "DonVi(M2/Hecta)": "m²"
    },
    {
        "DiaChi": "Đường số 7, Phường An Lạc, Quận Bình Tân, Tp Hồ Chí Minh",
        "LoaiHinhDat": "Đất thổ cư",
        "DienTichDat": "64 m²",
        "Gia/M2": "87,50 triệu/m²",
        "GiayToPhapLy": "Đã có sổ",
        "ChieuNgang": "4 m",
        "ChieuDai": "16 m"
    },
    {
        "DiaChi": "Đường Diên Hồng, Phường Hòa Xuân, Quận Cẩm Lệ, Đà Nẵng",
        "LoaiHinhDat": "Đất thổ cư",
        "DienTichDat": "100 m²",
        "Gia/M2": "53 triệu/m²",
        "GiayToPhapLy": "Đã có sổ",
        "HuongDat": "Đông Bắc",
        "DacDiemNha/Dat": "Mặt tiền",
        "ChieuNgang": "5 m",
        "ChieuDai": "20 m"
    },
    {
        "DiaChi": "38, ĐƯỜNG SỐ 7, Phường Hưng Phú, Quận Cái Răng, Cần Thơ",
        "LoaiHinhDat": "Đất thổ cư",
        "DienTichDat": "192 m²",
        "Gia/M2": "14,58 triệu/m²",
        "GiayToPhapLy": "Đã có sổ",
        "HuongDat": "Đông Nam",
        "DacDiemNha/Dat": "Mặt tiền",
        "ChieuNgang": "12 m",
        "ChieuDai": "16 m",
        "TenPhanKhu": "KHU 2",
        "DonVi(M2/Hecta)": "m²"
    },
    {
        "DiaChi": "Nguyễn Thiện Khiêm, Xã Tân Mỹ, Huyện Đức Hòa, Long An",
        "LoaiHinhDat": "Đất nền dự án",
        "DienTichDat": "82 m²",
        "Gia/M2": "14,63 triệu/m²",
        "GiayToPhapLy": "Đã có sổ",
        "HuongDat": "Đông Nam",
        "DacDiemNha/Dat": "Mặt tiền\nHẻm xe hơi\nThổ cư toàn bộ",
        "ChieuNgang": "4.5 m",
        "ChieuDai": "18.4 m",
        "DonVi(M2/Hecta)": "m²"
    },
    {
        "DiaChi": "Đường Nguyễn Văn Dương, Xã Đức Hòa Đông, Huyện Đức Hòa, Long An",
        "LoaiHinhDat": "Đất thổ cư",
        "DienTichDat": "540 m²",
        "Gia/M2": "13,89 triệu/m²",
        "GiayToPhapLy": "Đã có sổ",
        "DacDiemNha/Dat": "Thổ cư toàn bộ",
        "ChieuNgang": "18 m",
        "ChieuDai": "30 m",
        "DonVi(M2/Hecta)": "m²"
    },
    {
        "DiaChi": "Đường Lâm Thị Hố, Phường Tân Chánh Hiệp, Quận 12, Tp Hồ Chí Minh",
        "LoaiHinhDat": "Đất thổ cư",
        "DienTichDat": "350 m²",
        "Gia/M2": "51,43 triệu/m²",
        "GiayToPhapLy": "Đã có sổ",
        "HuongDat": "Bắc",
        "DacDiemNha/Dat": "Mặt tiền",
        "ChieuNgang": "9 m",
        "ChieuDai": "40 m",
        "DonVi(M2/Hecta)": "m²"
    },
    {
        "DiaChi": "Đường Thích Thiện Hoà, Xã Lê Minh Xuân, Huyện Bình Chánh, Tp Hồ Chí Minh",
        "LoaiHinhDat": "Đất thổ cư",
        "DienTichDat": "950 m²",
        "Gia/M2": "5,58 triệu/m²",
        "GiayToPhapLy": "Đã có sổ",
        "DacDiemNha/Dat": "Mặt tiền",
        "DonVi(M2/Hecta)": "m²"
    },
    {
        "DiaChi": "Đường Tỉnh lộ 7, Xã Thái Mỹ, Huyện Củ Chi, Tp Hồ Chí Minh",
        "LoaiHinhDat": "Đất thổ cư",
        "DienTichDat": "859 m²",
        "Gia/M2": "10 triệu/m²",
        "GiayToPhapLy": "Đã có sổ",
        "DacDiemNha/Dat": "Mặt tiền\nThổ cư 1 phần",
        "DonVi(M2/Hecta)": "m²"
    },
    {
        "DiaChi": "Đường Phạm Thế Hiển, Phường 7, Quận 8, Tp Hồ Chí Minh",
        "LoaiHinhDat": "Đất thổ cư",
        "DienTichDat": "59.1 m²",
        "Gia/M2": "38,07 triệu/m²",
        "GiayToPhapLy": "Đã có sổ",
        "HuongDat": "Tây Nam",
        "DacDiemNha/Dat": "Thổ cư toàn bộ",
        "ChieuNgang": "5.8 m",
        "ChieuDai": "10 m",
        "DonVi(M2/Hecta)": "m²"
    },
    {
        "DiaChi": "Đường Nguyễn Giản Thanh, Phường An Khê, Quận Thanh Khê, Đà Nẵng",
        "LoaiHinhDat": "Đất thổ cư",
        "DienTichDat": "90 m²",
        "Gia/M2": "48,33 triệu/m²",
        "GiayToPhapLy": "Đã có sổ",
        "HuongDat": "Đông",
        "DacDiemNha/Dat": "Mặt tiền",
        "ChieuNgang": "5 m",
        "ChieuDai": "18 m",
        "DonVi(M2/Hecta)": "m²"
    },
    {
        "DiaChi": "Đường Mỹ Phước - Tân Vạn, Phường Tân Đông Hiệp, Thành phố Dĩ An, Bình Dương",
        "LoaiHinhDat": "Đất thổ cư",
        "DienTichDat": "109.5 m²",
        "Gia/M2": "38,36 triệu/m²",
        "GiayToPhapLy": "Đã có sổ",
        "ChieuNgang": "6.4 m",
        "DonVi(M2/Hecta)": "m²"
    },
    {
        "DiaChi": "160, Phường Tăng Nhơn Phú A (Quận 9 cũ), Thành phố Thủ Đức, Tp Hồ Chí Minh",
        "LoaiHinhDat": "Đất thổ cư",
        "DienTichDat": "145 m²",
        "Gia/M2": "35,17 triệu/m²",
        "GiayToPhapLy": "Đã có sổ",
        "DacDiemNha/Dat": "Hẻm xe hơi",
        "ChieuNgang": "4.5 m"
    },
    {
        "DiaChi": "Phố Phú Thượng, Phường Phú Thượng, Quận Tây Hồ, Hà Nội",
        "LoaiHinhDat": "Đất thổ cư",
        "DienTichDat": "130 m²",
        "Gia/M2": "193,85 triệu/m²",
        "GiayToPhapLy": "Đã có sổ",
        "DacDiemNha/Dat": "Mặt tiền\nThổ cư toàn bộ\nHẻm xe hơi",
        "ChieuNgang": "6.8 m",
        "ChieuDai": "19.12 m",
        "DonVi(M2/Hecta)": "m²"
    },
    {
        "DiaChi": "Đường Số 6, Phường Bình Hưng Hoà B, Quận Bình Tân, Tp Hồ Chí Minh",
        "LoaiHinhDat": "Đất thổ cư",
        "DienTichDat": "75 m²",
        "Gia/M2": "69,33 triệu/m²",
        "GiayToPhapLy": "Đã có sổ",
        "DacDiemNha/Dat": "Hẻm xe hơi",
        "ChieuNgang": "5 m",
        "ChieuDai": "15 m",
        "DonVi(M2/Hecta)": "m²"
    },
    {
        "DiaChi": "Đường Số 2, Phường Tân Phú, Quận 7, Tp Hồ Chí Minh",
        "LoaiHinhDat": "Đất thổ cư",
        "DienTichDat": "42 m²",
        "Gia/M2": "60,71 triệu/m²",
        "GiayToPhapLy": "Đã có sổ",
        "DacDiemNha/Dat": "Hẻm xe hơi\nMặt tiền",
        "ChieuNgang": "7.5 m"
    },
    {
        "DiaChi": "Đường Số 25, Phường Hiệp Bình Chánh (Quận Thủ Đức cũ), Thành phố Thủ Đức, Tp Hồ Chí Minh",
        "LoaiHinhDat": "Đất thổ cư",
        "DienTichDat": "17 m²",
        "Gia/M2": "134,12 triệu/m²",
        "GiayToPhapLy": "Đã có sổ",
        "ChieuNgang": "7 m",
        "ChieuDai": "17 m"
    },
    {
        "DiaChi": "Đường ĐT. 824, Xã Hựu Thạnh, Huyện Đức Hòa, Long An",
        "LoaiHinhDat": "Đất thổ cư",
        "DienTichDat": "150 m²",
        "Gia/M2": "7,33 triệu/m²",
        "GiayToPhapLy": "Đã có sổ",
        "HuongDat": "Đông Nam",
        "DacDiemNha/Dat": "Mặt tiền",
        "ChieuNgang": "5 m",
        "ChieuDai": "30 m",
        "DonVi(M2/Hecta)": "m²"
    },
    {
        "DiaChi": "Phan Thị Vẽ, Xã An Nhơn Tây, Huyện Củ Chi, Tp Hồ Chí Minh",
        "LoaiHinhDat": "Đất nông nghiệp",
        "DienTichDat": "7835 m²",
        "Gia/M2": "2,11 triệu/m²",
        "GiayToPhapLy": "Đã có sổ",
        "DacDiemNha/Dat": "Mặt tiền\nChưa có thổ cư",
        "DonVi(M2/Hecta)": "m²"
    },
    {
        "DiaChi": "., Xã Minh Hưng, Huyện Chơn Thành, Bình Phước",
        "LoaiHinhDat": "Đất thổ cư",
        "DienTichDat": "440 m²",
        "Gia/M2": "615.909 đ/m²",
        "GiayToPhapLy": "Đã có sổ",
        "DacDiemNha/Dat": "Mặt tiền",
        "DonVi(M2/Hecta)": "m²"
    },
    {
        "DiaChi": "Đường Lê Thị Riêng, Phường 1, Thành phố Sa Đéc, Đồng Tháp",
        "LoaiHinhDat": "Đất nông nghiệp",
        "DienTichDat": "650 m²",
        "Gia/M2": "9,23 triệu/m²",
        "GiayToPhapLy": "Đã có sổ",
        "DonVi(M2/Hecta)": "m²"
    },
    {
        "DiaChi": "Trần Đình Tri, Phường Hòa Minh, Quận Liên Chiểu, Đà Nẵng",
        "LoaiHinhDat": "Đất thổ cư",
        "DienTichDat": "66 m²",
        "Gia/M2": "35,61 triệu/m²",
        "GiayToPhapLy": "Đã có sổ",
        "ChieuNgang": "6 m",
        "ChieuDai": "11 m",
        "DonVi(M2/Hecta)": "m²"
    },
    {
        "DiaChi": "Đường Hà Huy Giáp, Phường Thạnh Lộc, Quận 12, Tp Hồ Chí Minh",
        "LoaiHinhDat": "Đất thổ cư",
        "DienTichDat": "60 m²",
        "Gia/M2": "61,65 triệu/m²",
        "GiayToPhapLy": "Đã có sổ",
        "DacDiemNha/Dat": "Hẻm xe hơi",
        "ChieuNgang": "4.3 m",
        "ChieuDai": "15 m",
        "DonVi(M2/Hecta)": "m²"
    },
    {
        "DiaChi": "Đường Trần Văn Ơn, Phường Tân Sơn Nhì, Quận Tân Phú, Tp Hồ Chí Minh",
        "LoaiHinhDat": "Đất thổ cư",
        "DienTichDat": "100 m²",
        "Gia/M2": "75 triệu/m²",
        "GiayToPhapLy": "Đã có sổ",
        "DacDiemNha/Dat": "Hẻm xe hơi\nNở hậu\nThổ cư toàn bộ",
        "ChieuNgang": "5 m",
        "ChieuDai": "20 m",
        "DonVi(M2/Hecta)": "m²"
    },
    {
        "DiaChi": "Đường Trương Vĩnh Nguyên, Phường Phú Thứ, Quận Cái Răng, Cần Thơ",
        "LoaiHinhDat": "Đất thổ cư",
        "DienTichDat": "250 m²",
        "Gia/M2": "4,40 triệu/m²",
        "GiayToPhapLy": "Đã có sổ",
        "HuongDat": "Tây Nam",
        "ChieuNgang": "7.8 m",
        "ChieuDai": "32.2 m"
    },
    {
        "DiaChi": "Đường số 16, Phường Linh Trung (Quận Thủ Đức cũ), Thành phố Thủ Đức, Tp Hồ Chí Minh",
        "LoaiHinhDat": "Đất thổ cư",
        "DienTichDat": "80 m²",
        "Gia/M2": "57,50 triệu/m²",
        "GiayToPhapLy": "Đã có sổ",
        "DacDiemNha/Dat": "Hẻm xe hơi",
        "ChieuNgang": "4 m",
        "ChieuDai": "20 m"
    },
    {
        "DiaChi": "Đường Đại Học quốc gia, Phường Đông Hòa, Thành phố Dĩ An, Bình Dương",
        "LoaiHinhDat": "Đất thổ cư",
        "DienTichDat": "225.6 m²",
        "Gia/M2": "22,61 triệu/m²",
        "GiayToPhapLy": "Đã có sổ",
        "HuongDat": "Đông",
        "ChieuNgang": "9.5 m",
        "DonVi(M2/Hecta)": "m²"
    },
    {
        "DiaChi": "Lê Văn Lương, Xã Nhơn Đức, Huyện Nhà Bè, Tp Hồ Chí Minh",
        "LoaiHinhDat": "Đất thổ cư",
        "DienTichDat": "94 m²",
        "Gia/M2": "35,11 triệu/m²",
        "GiayToPhapLy": "Đã có sổ",
        "HuongDat": "Đông Nam",
        "DacDiemNha/Dat": "Mặt tiền\nHẻm xe hơi\nThổ cư toàn bộ",
        "ChieuNgang": "10 m",
        "ChieuDai": "10 m"
    },
    {
        "DiaChi": "Phố Đàm Quang Trung, Phường Long Biên, Quận Long Biên, Hà Nội",
        "LoaiHinhDat": "Đất thổ cư",
        "DienTichDat": "67 m²",
        "Gia/M2": "114,66 triệu/m²",
        "GiayToPhapLy": "Đã có sổ",
        "DacDiemNha/Dat": "Hẻm xe hơi\nThổ cư toàn bộ",
        "ChieuNgang": "4.1 m",
        "DonVi(M2/Hecta)": "m²"
    },
    {
        "DiaChi": "La, Xã Ngọc Định, Huyện Định Quán, Đồng Nai",
        "LoaiHinhDat": "Đất nông nghiệp",
        "DienTichDat": "42980 m²",
        "Gia/M2": "202.187 đ/m²",
        "GiayToPhapLy": "Đã có sổ",
        "DacDiemNha/Dat": "Hẻm xe hơi"
    },
    {
        "DiaChi": "Đường Tả Thanh Oai, Xã Tả Thanh Oai, Huyện Thanh Trì, Hà Nội",
        "LoaiHinhDat": "Đất thổ cư",
        "DienTichDat": "57 m²",
        "Gia/M2": "82,46 triệu/m²",
        "GiayToPhapLy": "Đã có sổ",
        "DacDiemNha/Dat": "Mặt tiền",
        "ChieuNgang": "4 m"
    },
    {
        "DiaChi": "Đường số 16, Phường Linh Trung (Quận Thủ Đức cũ), Thành phố Thủ Đức, Tp Hồ Chí Minh",
        "LoaiHinhDat": "Đất thổ cư",
        "DienTichDat": "80 m²",
        "Gia/M2": "57,50 triệu/m²",
        "GiayToPhapLy": "Đã có sổ",
        "DacDiemNha/Dat": "Hẻm xe hơi",
        "ChieuNgang": "4 m",
        "ChieuDai": "20 m"
    },
    {
        "DiaChi": "Dx604 nhựa 7.5m, Phường Hòa Lợi, Thị xã Bến Cát, Bình Dương",
        "LoaiHinhDat": "Đất thổ cư",
        "DienTichDat": "115 m²",
        "Gia/M2": "9,57 triệu/m²",
        "GiayToPhapLy": "Đã có sổ",
        "HuongDat": "Nam",
        "DacDiemNha/Dat": "Mặt tiền\nThổ cư 1 phần\nHẻm xe hơi",
        "ChieuNgang": "6 m",
        "ChieuDai": "25 m"
    },
    {
        "DiaChi": "Đường Đại An 5, Phường Hoà Quý, Quận Ngũ Hành Sơn, Đà Nẵng",
        "LoaiHinhDat": "Đất thổ cư",
        "DienTichDat": "111 m²",
        "Gia/M2": "31,08 triệu/m²",
        "GiayToPhapLy": "Đã có sổ",
        "HuongDat": "Đông Nam",
        "DacDiemNha/Dat": "Mặt tiền",
        "ChieuNgang": "6 m",
        "ChieuDai": "18.5 m",
        "DonVi(M2/Hecta)": "m²"
    },
    {
        "DiaChi": "Đường Lò Lu, Phường Trường Thạnh (Quận 9 cũ), Thành phố Thủ Đức, Tp Hồ Chí Minh",
        "LoaiHinhDat": "Đất thổ cư",
        "DienTichDat": "64 m²",
        "Gia/M2": "57,81 triệu/m²",
        "GiayToPhapLy": "Đã có sổ",
        "ChieuNgang": "4 m",
        "ChieuDai": "16 m",
        "DonVi(M2/Hecta)": "m²"
    },
    {
        "DiaChi": "Ia Krêl, Xã Ia Krêl, Huyện Đức Cơ, Gia Lai",
        "LoaiHinhDat": "Đất thổ cư",
        "DienTichDat": "175 m²",
        "Gia/M2": "1,60 triệu/m²",
        "GiayToPhapLy": "Đã có sổ",
        "DacDiemNha/Dat": "Thổ cư toàn bộ",
        "ChieuNgang": "7 m",
        "ChieuDai": "25 m",
        "DonVi(M2/Hecta)": "m²"
    },
    {
        "DiaChi": "Đường Nguyễn Tri Phương, Phường Dĩ An, Thành phố Dĩ An, Bình Dương",
        "LoaiHinhDat": "Đất thổ cư",
        "DienTichDat": "73 m²",
        "Gia/M2": "32,19 triệu/m²",
        "GiayToPhapLy": "Đã có sổ",
        "HuongDat": "Đông Bắc",
        "DacDiemNha/Dat": "Hẻm xe hơi",
        "ChieuNgang": "5 m",
        "ChieuDai": "14 m"
    },
    {
        "DiaChi": "Đường Thạnh Xuân 13, Phường Thạnh Xuân, Quận 12, Tp Hồ Chí Minh",
        "LoaiHinhDat": "Đất thổ cư",
        "DienTichDat": "316 m²",
        "Gia/M2": "30,70 triệu/m²",
        "GiayToPhapLy": "Đã có sổ",
        "DacDiemNha/Dat": "Hẻm xe hơi\nThổ cư 1 phần",
        "ChieuNgang": "7.7 m",
        "ChieuDai": "48 m",
        "DonVi(M2/Hecta)": "m²"
    }
]